Workbook

Sheet Outputs
B2: Dashboard and Output
B3: all figures in millions of New Taiwan Dollors NTD unless stated
F6: Enterprise Value | N6: Price per Share
F7: Terminal Growth Rate | N7: Terminal Growth Rate
C8: =Model!D546 -> 66837912 | D8: =Model!E546 -> 0.0037290889 | E8: =Model!F546 -> 0.0049629316 | F8: =Model!G546 -> 0.0061922463 | G8: =Model!H546 -> 0.0074170718 | H8: =Model!I546 -> 0.008637446 | L8: =Model!M546 -> 0.0037290889 | M8: =Model!N546 -> 0.0049629316 | N8: =Model!O546 -> 0.0061922463 | O8: =Model!P546 -> 0.0074170718 | P8: =Model!Q546 -> 0.008637446 | R8: Quarterly adjustmenst have been done to all the inputs of the sensitivity table
B9: WACC | C9: =Model!D547 -> 0.018244601 | D9: =Model!E547 -> 69393180 | E9: =Model!F547 -> 75631955 | F9: =Model!G547 -> 83118185 | G9: =Model!H547 -> 92267688 | H9: =Model!I547 -> 1.037042e+08 | J9: WACC | K9: =Model!L547 -> 0.018244601 | L9: =Model!M547 -> 2752.2581 | M9: =Model!N547 -> 2992.8402 | N9: =Model!O547 -> 3281.5271 | O9: =Model!P547 -> 3634.3539 | P9: =Model!Q547 -> 4075.3731 | S9: WACC annual | U9: WACC quarter | W9: TGR annual | Y9: TGR quarter
C10: =Model!D548 -> 0.020015981 | D10: =Model!E548 -> 61969610 | E10: =Model!F548 -> 66865974 | F10: =Model!G548 -> 72613618 | G10: =Model!H548 -> 79455767 | H10: =Model!I548 -> 87738056 | K10: =Model!L548 -> 0.020015981 | L10: =Model!M548 -> 2465.9875 | M10: =Model!N548 -> 2654.803 | N10: =Model!O548 -> 2876.4459 | O10: =Model!P548 -> 3140.2956 | P10: =Model!Q548 -> 3459.6805 | S10: 0.0775 | U10: =((1+S10)^(1/4))-1 -> 0.018836088 | W10: 0.015 | Y10: =((1+W10)^(1/4))-1 -> 0.0037290889
C11: =Model!D549 -> 0.021231269 | D11: =Model!E549 -> 57745561 | E11: =Model!F549 -> 61955931 | F11: =Model!G549 -> 66837912 | G11: =Model!H549 -> 72566199 | H11: =Model!I549 -> 79381823 | K11: =Model!L549 -> 0.021231269 | L11: =Model!M549 -> 2303.098 | M11: =Model!N549 -> 2465.46 | N11: =Model!O549 -> 2653.7209 | O11: =Model!P549 -> 2874.6173 | P11: =Model!Q549 -> 3137.4441 | S11: 0.0825 | U11: =((1+S11)^(1/4))-1 -> 0.020015981 | W11: 0.02 | Y11: =((1+W11)^(1/4))-1 -> 0.0049629316
C12: =Model!D550 -> 0.022947935 | D12: =Model!E550 -> 52688995 | E12: =Model!F550 -> 56150766 | F12: =Model!G550 -> 60106862 | G12: =Model!H550 -> 64671358 | H12: =Model!I550 -> 69996355 | K12: =Model!L550 -> 0.022947935 | L12: =Model!M550 -> 2108.1047 | M12: =Model!N550 -> 2241.5989 | N12: =Model!O550 -> 2394.1555 | O12: =Model!P550 -> 2570.1733 | P12: =Model!Q550 -> 2775.518 | S12: =Inputs!N83 -> 0.087668161 | U12: =((1+S12)^(1/4))-1 -> 0.021231269 | W12: 0.025 | Y12: =((1+W12)^(1/4))-1 -> 0.0061922463
C13: =Model!D551 -> 0.024695077 | D13: =Model!E551 -> 48392772 | E13: =Model!F551 -> 51279555 | F13: =Model!G551 -> 54538632 | G13: =Model!H551 -> 58247030 | H13: =Model!I551 -> 62504602 | K13: =Model!L551 -> 0.024695077 | L13: =Model!M551 -> 1942.4321 | M13: =Model!N551 -> 2053.7534 | N13: =Model!O551 -> 2179.4312 | O13: =Model!P551 -> 2322.4359 | P13: =Model!Q551 -> 2486.618 | S13: 0.095 | U13: =((1+S13)^(1/4))-1 -> 0.022947935 | W13: 0.03 | Y13: =((1+W13)^(1/4))-1 -> 0.0074170718
S14: 0.1025 | U14: =((1+S14)^(1/4))-1 -> 0.024695077 | W14: 0.035 | Y14: =((1+W14)^(1/4))-1 -> 0.008637446
F16: Equity Value | N16: Upside/(Downside) to Current Price
F17: Terminal Growth Rate | N17: Terminal Growth Rate
D18: =Model!E556 -> 0.0037290889 | E18: =Model!F556 -> 0.0049629316 | F18: =Model!G556 -> 0.0061922463 | G18: =Model!H556 -> 0.0074170718 | H18: =Model!I556 -> 0.008637446 | L18: =Model!M556 -> 0.0037290889 | M18: =Model!N556 -> 0.0049629316 | N18: =Model!O556 -> 0.0061922463 | O18: =Model!P556 -> 0.0074170718 | P18: =Model!Q556 -> 0.008637446
B19: WACC | C19: =Model!D557 -> 0.018244601 | D19: =Model!E557 -> 71371557 | E19: =Model!F557 -> 77610333 | F19: =Model!G557 -> 85096562 | G19: =Model!H557 -> 94246066 | H19: =Model!I557 -> 1.0568257e+08 | J19: WACC | K19: =Model!L557 -> 0.018244601 | L19: =Model!M557 -> 0.17117366 | M19: =Model!N557 -> 0.27354903 | N19: =Model!O557 -> 0.39639453 | O19: =Model!P557 -> 0.54653358 | P19: =Model!Q557 -> 0.73420131
C20: =Model!D558 -> 0.020015981 | D20: =Model!E558 -> 63947987 | E20: =Model!F558 -> 68844351 | F20: =Model!G558 -> 74591996 | G20: =Model!H558 -> 81434145 | H20: =Model!I558 -> 89716434 | K20: =Model!L558 -> 0.020015981 | L20: =Model!M558 -> 0.049356367 | M20: =Model!N558 -> 0.1297034 | N20: =Model!O558 -> 0.22401954 | O20: =Model!P558 -> 0.33629599 | P20: =Model!Q558 -> 0.47220445
C21: =Model!D559 -> 0.021231269 | D21: =Model!E559 -> 59723938 | E21: =Model!F559 -> 63934308 | F21: =Model!G559 -> 68816289 | G21: =Model!H559 -> 74544576 | H21: =Model!I559 -> 81360200 | K21: =Model!L559 -> 0.021231269 | L21: =Model!M559 -> -0.019958286 | M21: =Model!N559 -> 0.049131904 | N21: =Model!O559 -> 0.12924292 | O21: =Model!P559 -> 0.22324141 | P21: =Model!Q559 -> 0.33508259
C22: =Model!D560 -> 0.022947935 | D22: =Model!E560 -> 54667372 | E22: =Model!F560 -> 58129144 | F22: =Model!G560 -> 62085239 | G22: =Model!H560 -> 66649735 | H22: =Model!I560 -> 71974733 | K22: =Model!L560 -> 0.022947935 | L22: =Model!M560 -> -0.10293415 | M22: =Model!N560 -> -0.046128109 | N22: =Model!O560 -> 0.018789555 | O22: =Model!P560 -> 0.093690781 | P22: =Model!Q560 -> 0.18107149
C23: =Model!D561 -> 0.024695077 | D23: =Model!E561 -> 50371150 | E23: =Model!F561 -> 53257932 | F23: =Model!G561 -> 56517009 | G23: =Model!H561 -> 60225408 | H23: =Model!I561 -> 64482979 | K23: =Model!L561 -> 0.024695077 | L23: =Model!M561 -> -0.17343314 | M23: =Model!N561 -> -0.1260624 | N23: =Model!O561 -> -0.07258248 | O23: =Model!P561 -> -0.011729405 | P23: =Model!Q561 -> 0.058135337
E27: Enterprise | F27: Equity | G27: Equity
E28: Value | F28: Value | G28: Per Share | R28: As on June 1st June 2026
C29: Best Case | D29: 1 | E29: =Model!H547 -> 92267688 | F29: =Model!H557 -> 94246066 | G29: =F29/Inputs!$G$89 -> 3634.3539 | J29: 12-Month Target Price | L29: (NTD/sh) | M29: =SUM('Key Ratios & Metrics'!G225:J225)*Model!G574 -> 2881.004
C30: Base Case | D30: 2 | E30: =Model!G549 -> 66837912 | F30: =Model!G559 -> 68816289 | G30: =F30/Inputs!$G$89 -> 2653.7209 | J30: Near Term Target Price | L30: (NTD/sh) | M30: =Model!T531 -> 2653.7789
C31: Bear Case | D31: 3 | E31: =Model!E551 -> 48392772 | F31: =Model!E561 -> 50371150 | G31: =F31/Inputs!$G$89 -> 1942.4321 | J31: Current Price | L31: (NTD/sh) | M31: =Inputs!G90 -> 2350

Sheet Inputs
B1: Drivers and Inputs | K1: Forecasts | R1: Notes:
B2: all figures in millions of New Taiwan Dollors NTD unless stated | I2: 46203 | J2: 46295 | K2: 46386 | L2: 46476 | M2: 46568 | N2: Term
B4: Cost of Sales | I4: 0.335 | J4: 0.3325 | K4: 0.33 | L4: 0.3275 | M4: 0.325 | N4: 0.323 | R4: Most of revenue is by wafer business and growth from increasing demand for the HPC and AI
R5: in historicals tab revenue is calculated by both technology and platforms taken directly from the investors presentation
B6: SG&A | I6: 0.023 | J6: 0.021 | K6: 0.02 | L6: 0.0195 | M6: 0.019 | N6: 0.019 | R6: which is based on the % revenue contribution by each technology and platform
R7: under technology sub 7nm were given main priority for the revenue growth since these tech makes up most of the demand
B8: R&D | I8: 0.0595 | J8: 0.059 | K8: 0.0585 | L8: 0.058 | M8: 0.058 | N8: 0.058 | R8: escpecially 3nm, and newly developing 2nm not considered in modelling since its neither available in the market yet nor
R9: its specifications
B10: Account Recievables Days | I10: 28.25 | J10: 28.75 | K10: 28.5 | L10: 28 | M10: 27.75 | N10: 27.25
B11: Inventory Days | I11: 72.25 | J11: 72.5 | K11: 73 | L11: 73 | M11: 72 | N11: 72
B12: Account Payable Days | I12: 22.75 | J12: 23 | K12: 23.5 | L12: 24 | M12: 23 | N12: 24
B15: Taxes | I15: Assets & Depreciation
B17: Tax Rate | F17: 0.16 | I17: First Year Accounting Depreciation/ Depreciable First year Amount | N17: 1
B18: First Year Tax Depreciation | F18: 0.4 | I18: Usefull life: Existing assets | N18: 10
B19: Blended tax Depreciation Rate | F19: 0.2 | I19: Usefull life: New assets | N19: 12
B20: Tax basis for Assets | F20: 4108129.3 | G20: end of Q1 2026
B21: Tax Losses | F21: 0 | G21: end of Q1 2026 | I21: Net PP&E at the End of 2026FY | N21: 3954679
I22: Gross PP&E at the End of 2026FY | N22: 8052961.7
I23: Depreciable Assets | N23: 6755752
B25: Interest Rates | I25: Other Single Inputs
B27: Cash Balances | F27: 0.01 | I27: Dividend Payout ratio | N27: 0.23
B28: Revolving Credit Line | F28: 0.01125 | I28: NCI Dividend/Distribution | N28: 0
B29: Bonds | F29: 0.006 | I29: Total Debt | N29: =Historicals!K142 -> 1057259.7
B30: Bank Loans | F30: 0.005 | I30: Cash | N30: =Historicals!K83 -> 3035637
I31: Market Capitalization
B32: Dates
B34: Valuation Date | F34: 46143
B35: First Expected Cash Flow | F35: 46157
B36: First Quarter End for Forecast | F36: 46203
B37: First Forecast | F37: 46174
B38: Incorrect Date Set for Valuation? | F38: =IF(F34>F35,1,0) -> 0
B39: Incorrect Date Set for First Cash Flow? | F39: =IF(F35>F36,1,0) -> 0
B40: Days in Period
B43: Weighted Average Cost of Capital
J45: Avg | K45: Debt / | L45: Debt / | M45: Unlevered | N45: Levered
B46: Name | E46: Exchange | F46: Ticker | G46: Currency | H46: Debt | I46: Equity | J46: Tax Rate 1 | K46: Equity | L46: Capital | M46: Beta 2 | N46: Beta 3
B48: Samsung Electronics | E48: KRX | F48: 005930 | G48: KRW | H48: 28138800 | I48: 1500000000 | J48: =H48/I48 -> 0.0187592 | K48: 0.185 | L48: =H48/(I48+H48) -> 0.018413772 | M48: 1.49 | N48: =M48/(1+(1-J48)*K48) -> 1.2610772
B49: Semiconductor Manufacturing International Corp | G49: CNY | H49: 102805 | I49: 548500 | J49: 0.1125 | K49: =H49/I49 -> 0.18742935 | L49: =H49/(H49+I49) -> 0.15784464 | M49: 1.15 | N49: =M49/(1+(1-J49)*K49) -> 0.98598736
B50: Intel Corporation | E50: NASDAQ | F50: INTC | G50: USD | H50: 44086 | I50: 498428 | J50: =H50/I50 -> 0.088450087 | K50: 0.1 | L50: =H50/(I50+H50) -> 0.081262419 | M50: 1.5 | N50: =M50/(1+(1-J50)*K50) -> 1.3746901
B51: Gloabal Foundaries Inc | E51: NASDAQ | F51: GFS | G51: USD | H51: 1147 | I51: 37220 | J51: =H51/I51 -> 0.030816765 | K51: 0.27 | L51: =H51/(I51+H51) -> 0.029895483 | M51: 1.34 | N51: =M51/(1+(1-J51)*K51) -> 1.0620764
B52: United Microelectronics Corporation | E52: TWSE | F52: 2303 | G52: TWD | H52: 56740 | I52: 1515456 | J52: =H52/I52 -> 0.037440876 | K52: 0.032 | L52: =H52/(I52+H52) -> 0.036089648 | M52: 1.53 | N52: =M52/(1+(1-J52)*K52) -> 1.4842813
I54: Average | J54: =AVERAGE(J48:J52) -> 0.057593386 | K54: =AVERAGE(K48:K52) -> 0.15488587 | L54: =AVERAGE(L48:L52) -> 0.064701191 | M54: =AVERAGE(M48:M52) -> 1.402 | N54: =AVERAGE(N48:N52) -> 1.2336225
I55: Median | J55: =MEDIAN(J48:J52) -> 0.037440876 | K55: =MEDIAN(K48:K52) -> 0.185 | L55: =MEDIAN(L48:L52) -> 0.036089648 | M55: =MEDIAN(M48:M52) -> 1.49 | N55: =MEDIAN(N48:N52) -> 1.2610772
B58: Risk Premium for Equity | J58: Cost of Equity
R59: 10Y Taiwan Govt Bond Yield
B60: Market Risk Premium | G60: 0.0575 | J60: Risk Free Rate | N60: 0.0172 | R60: Equity Risk Premium : 6.2% adjusted for regional equity market volatility compared to local fixed income
B61: Average Unlevered Beta | G61: =N54 -> 1.2336225 | J61: Equity Risk Premium | N61: =G63 -> 0.073081506 | R61: MRP : using local appraoch5.5% to 6% The baseline mature-market risk premium evaluated globally, reflecting localized risk parameters mapped across East Asian tech hubs
B62: Levered Beta 4 | G62: =G61*(1+(1-N70)*G73) -> 1.2709827 | J62: Country Risk Premium | N62: 0 | R62: using Global Appoarch : Mature US base 4.3% + Country risk Premium taiwan's 0.78% making it around 5.1%
B63: Equity Risk Premium | G63: =G62*G60 -> 0.073081506 | J63: Cost of Equity | N63: =SUM(N60:N62) -> 0.090281506
B67: Capital Structure | J67: Cost of Debt
F68: Current | G68: Target
B69: Total Debt | E69: 1024500 | F69: =E69/E71 -> 0.035116283 | G69: 0.035 | J69: Pre-Tax Cost of Debt | N69: =N60+0.15% -> 0.0187
B70: Market Capitalization | E70: 28150000 | F70: =E70/E71 -> 0.96488372 | G70: =1-G69 -> 0.965 | J70: Tax Rate | N70: 0.165
B71: Total Capitalization | E71: =SUM(E69:E70) -> 29174500 | F71: =SUM(F69:F70) -> 1 | G71: =SUM(G69:G70) -> 1 | J71: After-Tax Cost of Debt | N71: =N69*(1-N70) -> 0.0156145
B73: Debt / Equity | F73: =F69/F70 -> 0.036394316 | G73: =G69/G70 -> 0.03626943
B76: NOTE: | J76: Weighted Average Cost of Capital
B77: Tax Rate is a 5-Year Average. | M77: Weight | N77: Cost
B78: Levered beta is based on 5-year monthly data. | J78: Debt Capital | M78: =G69 -> 0.035 | N78: =N71 -> 0.0156145
B79: Unlevered Beta = Levered Beta / (1 + (1 - Tax Rate) × Debt-to-Equity) | J79: Equity Capital | M79: =G70 -> 0.965 | N79: =N63 -> 0.090281506
B80: Levered Beta = Unlevered Beta x (1 + (1 - Tax rate) x (Debt-to-Equity))
J83: Weighted Average Cost of Capital | N83: =SUMPRODUCT(M78:M79,N78:N79) -> 0.087668161
J84: Terminal Growth Rate | N84: 0.025
B86: Valuation Input and Assumptions
B88: Net Cash | G88: 1978377.3
B89: Shares Oustanding | G89: 25932 | R89: shares Outsatnding in Millions
B90: Current Stock Price | E90: (NT$/sh) | G90: 2350 | R90: Current Price as on 1st June
B91: Terminal Growth Rate | G91: =N84 -> 0.025
B92: Terminal EBITDA Multiple | G92: 0 | R92: From the Peer EV/Ebitda Multiple but the issue is that we cant amount for the operational Depreciation as using the D&A from CFS will make the EBITDA resulting more or less thean gross profit or Operational Income
B93: Weighted Average Cost of Capital | G93: =N83 -> 0.087668161 | R93: But we have assuemd that 60% to 80% of operational cost will includes the Operational Depreciation that we can add to Operational income or netoff from gross profit to arrive at EBITDA
B94: Terminal Growth Greater than or equal to WACC | G94: =IF(G91>G93,1,0) -> 0 | R94: Based on Peers AVG Multiple is around 49 to51x
B97: Quarterly Adjustment
B98: WACC | C98: =((1+N83)^(1/4))-1 -> 0.021231269
B99: TGR | C99: =((1+N84)^(1/4))-1 -> 0.0061922463

Sheet Model
B1: Income Statement | G1: Actuals | P1: Forecasts | W1: Notes & References
B2: all figures in millions of New Taiwan Dollors NTD | G2: 45382 | H2: =EDATE(G2,3) -> 45473 | I2: =EDATE(H2,3) -> 45565 | J2: =EDATE(I2,3) -> 45656 | K2: =EDATE(J2,3) -> 45746 | L2: =EDATE(K2,3) -> 45838 | M2: =EDATE(L2,3) -> 45930 | N2: =EDATE(M2,3) -> 46021 | O2: =EDATE(N2,3) -> 46111 | ... T2: =EDATE(S2,3) -> 46568 | U2: Term
B4: Net Revenue | G4: 592644 | H4: 673510 | I4: 759692 | J4: 868461 | K4: 839254 | L4: 933792 | M4: 989918 | N4: 1046090 | O4: 1134103 | P4: =P161 -> 1248392.2 | Q4: =Q161 -> 1382472.3 | R4: =R161 -> 1536433 | S4: =S161 -> 1713637.5 | T4: =T161 -> 1917692.4 | U4: =U161 -> 2149498.4
B5: Cost of Revenue | G5: -278139 | H5: -315385 | I5: -320347 | J5: -356082 | K5: -345859 | L5: -386423 | M5: -401375 | N5: -394103 | O5: -382808 | P5: =P178*-1 -> -418211.4 | Q5: =Q178*-1 -> -459672.05 | R5: =R178*-1 -> -507022.89 | S5: =S178*-1 -> -561216.28 | T5: =T178*-1 -> -623250.02 | U5: =U178*-1 -> -694287.98
B6: Gross Profit | G6: 314505 | H6: 358125 | I6: 439345 | J6: 512379 | K6: 493395 | L6: 547369 | M6: 588543 | N6: 651987 | O6: 751295 | P6: =SUM(P4:P5) -> 830180.83 | Q6: =SUM(Q4:Q5) -> 922800.28 | R6: =SUM(R4:R5) -> 1029410.1 | S6: =SUM(S4:S5) -> 1152421.2 | T6: =SUM(T4:T5) -> 1294442.4 | U6: =SUM(U4:U5) -> 1455210.4
B8: Operating Expenses
B9: R&D Expenses | G9: -46109 | H9: -48058 | I9: -52783 | J9: -57232 | K9: -56547 | L9: -61280 | M9: -63743 | N9: -64857 | O9: -67757 | P9: =P180*-1 -> -74279.338 | Q9: =Q180*-1 -> -81565.868 | R9: =R180*-1 -> -89881.331 | S9: =S180*-1 -> -99390.975 | T9: =T180*-1 -> -111226.16 | U9: =U180*-1 -> -124670.91
B10: SG&A Eapenses | G10: -19248 | H10: -22238 | I10: -26295 | J10: -29108 | K10: -28639 | L10: -23228 | M10: -24022 | N10: -23333 | O10: -26249 | P10: =P179*-1 -> -28713.021 | Q10: =Q179*-1 -> -29031.919 | R10: =R179*-1 -> -30728.66 | S10: =S179*-1 -> -33415.931 | T10: =T179*-1 -> -36436.155 | U10: =U179*-1 -> -40840.469
B11: Total Operating Expenses | G11: -65357 | H11: -70296 | I11: -79078 | J11: -86340 | K11: -85186 | L11: -84508 | M11: -87765 | N11: -88190 | O11: -94006 | P11: =SUM(P9:P10) -> -102992.36 | Q11: =SUM(Q9:Q10) -> -110597.79 | R11: =SUM(R9:R10) -> -120609.99 | S11: =SUM(S9:S10) -> -132806.91 | T11: =SUM(T9:T10) -> -147662.31 | U11: =SUM(U9:U10) -> -165511.38
B13: Other operating Income and Expenses | G13: -130 | H13: -1273 | I13: 499 | J13: -326 | K13: -1128 | L13: 562 | M13: -93 | N13: 1106 | O13: 1677 | P13: 0 | Q13: 0 | R13: 0 | S13: 0 | T13: 0 | U13: 0
B15: Income from Operations | G15: 249018 | H15: 286556 | I15: 360766 | J15: 425713 | K15: 407081 | L15: 463423 | M15: 500685 | N15: 564903 | O15: 658966 | P15: =P6+P11+P13 -> 727188.47 | Q15: =Q6+Q11+Q13 -> 812202.5 | R15: =R6+R11+R13 -> 908800.13 | S15: =S6+S11+S13 -> 1019614.3 | T15: =T6+T11+T13 -> 1146780 | U15: =U6+U11+U13 -> 1289699
W16: Share of Profits and Associated | AH16: =AH17*P4 -> 1872.5883 | AI16: =AI17*Q4 -> 1935.4613 | AJ16: =AJ17*R4 -> 2151.0062 | AK16: =AK17*S4 -> 2399.0925 | AL16: =AL17*T4 -> 2493.0001 | AM16: =AM17*U4 -> 2794.3479
B17: Non operating Income and Expenses | W17: Share of Profit as % Rev | Y17: =G18/G4 -> 0.0014814965 | Z17: =H18/H4 -> 0.0017104423 | AA17: =I18/I4 -> 0.0020547801 | AB17: =J18/J4 -> 0.0014842348 | AC17: =K18/K4 -> 0.001630019 | AD17: =L18/L4 -> 0.0013086426 | AE17: =M18/M4 -> 0.001438503 | AF17: =N18/N4 -> 0.00141766 | AG17: =O18/O4 -> 0.0014857557 | AH17: 0.0015 | AI17: 0.0014 | AJ17: 0.0014 | AK17: 0.0014 | AL17: 0.0013 | AM17: 0.0013
B18: Share of Profits and Associated | G18: 878 | H18: 1152 | I18: 1561 | J18: 1289 | K18: 1368 | L18: 1222 | M18: 1424 | N18: 1483 | O18: 1685 | P18: =AH16 -> 1872.5883 | Q18: =AI16 -> 1935.4613 | R18: =AJ16 -> 2151.0062 | S18: =AK16 -> 2399.0925 | T18: =AL16 -> 2493.0001 | U18: =AM16 -> 2794.3479
B19: Net interest Income (Expenses) | G19: 16661 | H19: 18341 | I19: 19966 | J19: 21750 | K19: 22182 | L19: 21501 | M19: 23222 | N19: 26463 | O19: 26146 | P19: =P424 -> 26769.667 | Q19: =Q424 -> 30552.204 | R19: =R424 -> 34450.595 | S19: =S424 -> 38634.096 | T19: =T424 -> 42747.068 | U19: =U424 -> 51589.506 | W19: Net interest Income (Expenses) | AH19: =P4*AH20 -> 29961.414 | AI19: =Q4*AI20 -> 34561.808 | AJ19: =R4*AJ20 -> 39947.258 | AK19: =S4*AK20 -> 46268.212 | AL19: =T4*AL20 -> 53695.387 | AM19: =U4*AM20 -> 62335.453
B20: Other gains and Losses | G20: -14 | H20: 262 | I20: 1894 | J20: 46 | K20: 264 | L20: 6890 | M20: 38 | N20: -486 | O20: 1003 | P20: 0 | Q20: 0 | R20: 0 | S20: 0 | T20: 0 | U20: 0 | W20: interest income as % of rev | Y20: =G19/G4 -> 0.028112999 | Z20: =H19/H4 -> 0.027231964 | AA20: =I19/I4 -> 0.026281704 | AB20: =J19/J4 -> 0.025044303 | AC20: =K19/K4 -> 0.026430616 | AD20: =L19/L4 -> 0.02302547 | AE20: =M19/M4 -> 0.023458509 | AF20: =N19/N4 -> 0.025297059 | AG20: =O19/O4 -> 0.023054343 | AH20: 0.024 | AI20: 0.025 | AJ20: 0.026 | AK20: 0.027 | AL20: 0.028 | AM20: 0.029
B21: Total Non Operating Income and Expenses | G21: 17525 | H21: 19755 | I21: 23421 | J21: 23085 | K21: 23814 | L21: 29613 | M21: 24684 | N21: 27460 | O21: 28834 | P21: =SUM(P18:P20) -> 28642.255 | Q21: =SUM(Q18:Q20) -> 32487.665 | R21: =SUM(R18:R20) -> 36601.601 | S21: =SUM(S18:S20) -> 41033.189 | T21: =SUM(T18:T20) -> 45240.068 | U21: =SUM(U18:U20) -> 54383.854 | W21: interst income as % of Cash and equivalents | Y21: =G19/G83 -> 0.0098109994 | Z21: =H19/H83 -> 0.010194389 | AA21: =I19/I83 -> 0.010582044 | AB21: =J19/J83 -> 0.010222657 | AC21: =K19/K83 -> 0.0092625534 | AD21: =L19/L83 -> 0.0090931621 | AE21: =M19/M83 -> 0.0093987313 | AF21: =N19/N83 -> 0.0095608298 | ... AL21: =T19/T83 -> 0.0082860006
B23: Income before Income Taxes | G23: 266543 | H23: 306311 | I23: 384187 | J23: 448798 | K23: 430895 | L23: 493036 | M23: 525369 | N23: 592363 | O23: 687800 | P23: =P15+P21 -> 755830.73 | Q23: =Q15+Q21 -> 844690.16 | R23: =R15+R21 -> 945401.73 | S23: =S15+S21 -> 1060647.5 | T23: =T15+T21 -> 1192020.1 | U23: =U15+U21 -> 1344082.9
B25: Income Tax Expenses | G25: -41322 | H25: -58649 | I25: -59107 | J25: -74329 | K25: -70162 | L25: -95543 | M25: -73614 | N25: -86947 | O25: -114999 | P25: =P316*-1 -> -120932.92 | Q25: =Q316*-1 -> -135150.43 | R25: =R316*-1 -> -151264.28 | S25: =S316*-1 -> -169703.6 | T25: =T316*-1 -> -190723.22 | U25: =U316*-1 -> -215053.26
B27: Net Income | G27: 225221 | H27: 247662 | I27: 325080 | J27: 374469 | K27: 360733 | L27: 397493 | M27: 451755 | N27: 505416 | O27: 572480 | P27: =P23+P25 -> 634897.81 | Q27: =Q23+Q25 -> 709539.74 | R27: =R23+R25 -> 794137.45 | S27: =S23+S25 -> 890943.9 | T27: =T23+T25 -> 1001296.9 | U27: =U23+U25 -> 1129029.6
B29: Other Comprehesive Income (Losses) | G29: 41274 | H29: 13464 | I29: -21056 | J29: 37903 | K29: 31897 | L29: -254502 | M29: 95202 | N29: 71076 | O29: 53996 | P29: 40470 | Q29: 40470 | R29: 40470 | S29: 40470 | T29: 40470 | U29: 40470
B30: Comprehensive Income | G30: 266495 | H30: 261126 | I30: 304024 | J30: 412372 | K30: 392630 | L30: 142991 | M30: 546957 | N30: 576492 | O30: 626797 | P30: =P27+P29 -> 675367.81 | Q30: =Q27+Q29 -> 750009.74 | R30: =R27+R29 -> 834607.45 | S30: =S27+S29 -> 931413.9 | T30: =T27+T29 -> 1041766.9 | U30: =U27+U29 -> 1169499.6
B32: net income (losses) attributable to shareholder of the parent | G32: 225485 | H32: 247845 | I32: 325258 | J32: 374680 | K32: 361564 | L32: 398273 | M32: 452302 | N32: 505744 | O32: 572160 | P32: =P34-P33 -> 635231.81 | Q32: =Q34-Q33 -> 709873.74 | R32: =R34-R33 -> 794471.45 | S32: =S34-S33 -> 891277.9 | T32: =T34-T33 -> 1001630.9 | U32: =U34-U33 -> 1129363.6
B33: NCI | G33: -264 | H33: -183 | I33: -178 | J33: -211 | K33: -831 | L33: -780 | M33: -547 | N33: -328 | O33: 320 | P33: -334 | Q33: -334 | R33: -334 | S33: -334 | T33: -334 | U33: -334
G34: 225221 | H34: 247662 | I34: 325080 | J34: 374469 | K34: 360733 | L34: 397493 | M34: 451755 | N34: 505416 | O34: 572480 | P34: =P27 -> 634897.81 | Q34: =Q27 -> 709539.74 | R34: =R27 -> 794137.45 | S34: =S27 -> 890943.9 | T34: =T27 -> 1001296.9 | U34: =U27 -> 1129029.6
B36: Cash flow Statement
B37: all figures in millions of New Taiwan Dollors NTD | G37: =G2 -> 45382 | H37: =H2 -> 45473 | I37: =I2 -> 45565 | J37: =J2 -> 45656 | K37: =K2 -> 45746 | L37: =L2 -> 45838 | M37: =M2 -> 45930 | N37: =N2 -> 46021 | ... U37: =U2 -> Term
B39: Cash from Operating Activities
B40: Income Before Income Tax | G40: 266543 | H40: 306311 | I40: 384187 | J40: 448798 | K40: 430895 | L40: 493036 | M40: 525369 | N40: 592363 | O40: 687800 | P40: =P23 -> 755830.73 | Q40: =Q23 -> 844690.16 | R40: =R23 -> 945401.73 | S40: =S23 -> 1060647.5 | T40: =T23 -> 1192020.1
B41: D&A | G41: 159023 | H41: 165166 | I41: 168229 | J41: 170378 | K41: 175139 | L41: 188058 | M41: 162787 | N41: 162112 | O41: 165450 | P41: =P241 -> 176696.25 | Q41: =Q241 -> 185192.7 | R41: =R241 -> 194475.31 | S41: =S241 -> 204650.03 | T41: =T241 -> 215836.57
B42: Share of Profits of Associates | G42: -878 | H42: -1152 | I42: -1561 | J42: -1289 | K42: -1368 | L42: -1222 | M42: -1424 | N42: -1483 | O42: -1685 | P42: =P18*-1 -> -1872.5883 | Q42: =Q18*-1 -> -1935.4613 | R42: =R18*-1 -> -2151.0062 | S42: =S18*-1 -> -2399.0925 | T42: =T18*-1 -> -2493.0001
B43: Income Taxes Paid | G43: -1051 | H43: -88103 | I43: -93295 | J43: -1190 | K43: -1537 | L43: -127347 | M43: -137266 | N43: -1407 | O43: -1501 | P43: =P25-O25 -> -5933.9167 | Q43: =Q25-P25 -> -14217.509 | R43: =R25-Q25 -> -16113.85 | S43: =S25-R25 -> -18439.324 | T43: =T25-S25 -> -21019.617
B44: changes in working Capital & Others | G44: 12674 | H44: -4554 | I44: -65567 | J44: 3508 | K44: 22445 | L44: -55461 | M44: -122637 | N44: -26076 | O44: -151088 | P44: =P205 -> -33750.746 | Q44: =Q205 -> -70992.409 | R44: =R205 -> -77642.57 | S44: =S205 -> -81694.028 | T44: =T205 -> -71700.013
B45: Net Cash from Operating Activities | G45: 436311 | H45: 377668 | I45: 391993 | J45: 620205 | K45: 625574 | L45: 497064 | M45: 426829 | N45: 725509 | O45: 689976 | P45: =SUM(P40:P44) -> 890969.73 | Q45: =SUM(Q40:Q44) -> 942737.48 | R45: =SUM(R40:R44) -> 1043969.6 | S45: =SUM(S40:S44) -> 1162765.1 | T45: =SUM(T40:T44) -> 1312644.1
B47: Cash Flow From Investing Activities
B48: Interest Received | G48: 17410 | H48: 19195 | I48: 21356 | J48: 18473 | K48: 24419 | L48: 26025 | M48: 22351 | N48: 26160 | O48: 26746 | P48: =P19 -> 26769.667 | Q48: =Q19 -> 30552.204 | R48: =R19 -> 34450.595 | S48: =S19 -> 38634.096 | T48: =T19 -> 42747.068 | AI48: =Q47 -> 0 | AJ48: =R47 -> 0 | AK48: =S47 -> 0 | AL48: =T47 -> 0
B49: Cash Dividend Received | G49: 90 | H49: 805 | I49: 2405 | J49: 207 | K49: 95 | L49: 1091 | M49: 2705 | N49: 49 | O49: 1041 | P49: =AVERAGE(G49:O49) -> 943.11111 | Q49: =AVERAGE(H49:P49) -> 1037.9012 | R49: =AVERAGE(I49:Q49) -> 1063.7791 | S49: =AVERAGE(J49:R49) -> 914.75461 | T49: =AVERAGE(K49:S49) -> 993.39401 | U49: << | W49: Assumed as average of previous 9 quarters | Y49: =G56 -> -763 | Z49: =H56 -> 6673 | AA49: =I56 -> 7446 | AB49: =J56 -> 51560 | AC49: =K56 -> 32808 | AD49: =L56 -> 29749 | AE49: =M56 -> 3823 | AF49: =N56 -> -4939 | AG49: =O56 -> -5375 | AH49: =AH50*P4 -> 18726.343 | AI49: =AI50*Q4 -> 12642.611 | AJ49: =AJ50*R4 -> 29557.726 | AK49: =AK50*S4 -> 25380.726 | AL49: =AL50*T4 -> 35478.187
B50: Acquisitions of : | Y50: =Y49/G4 -> -0.0012874508 | Z50: =Z49/H4 -> 0.0099077965 | AA50: =AA49/I4 -> 0.0098013405 | AB50: =AB49/J4 -> 0.05936939 | AC50: =AC49/K4 -> 0.03909186 | AD50: =AD49/L4 -> 0.031858273 | AE50: =AE49/M4 -> 0.003861936 | AF50: =AF49/N4 -> -0.0047213911 | AG50: =AG49/O4 -> -0.0047394284 | AH50: 0.015000368 | AI50: 0.0091449287 | AJ50: 0.019237888 | AK50: 0.014811024 | AL50: 0.018500458
B51: PPE | G51: -181305 | H51: -205674 | I51: -207079 | J51: -361949 | K51: -330827 | L51: -297226 | M51: -287452 | N51: -356906 | O51: -350763 | P51: =P212*-1 -> -374517.67 | Q51: =Q212*-1 -> -407829.34 | R51: =R212*-1 -> -445565.57 | S51: =S212*-1 -> -488386.69 | T51: =T212*-1 -> -536953.87
B52: Marketable Financial Instruments | G52: -45800 | H52: -63263 | I52: -54209 | J52: -77351 | K52: -70741 | L52: -61989 | M52: -50445 | N52: -72197 | O52: -91621 | P52: -96235 | Q52: -74239 | R52: -85734 | S52: -82749 | T52: -59827 | U52: << | W52: Marketable Fin instrumenst acquisition is xtimes of disposals assumed to increase. From 1.3 to 1.4 from previous years
B53: Proceeds from Disposal or Redemption of: | W53: Proceeds from Disposal or Redemption of:
B54: PPE | G54: 337 | H54: 156 | I54: 146 | J54: 256 | K54: 128 | L54: 117 | M54: 70 | N54: 482 | O54: 1813 | P54: =AH54 -> 337.0659 | Q54: =AI54 -> 407.82934 | R54: =AJ54 -> 490.12213 | S54: =AK54 -> 586.06402 | T54: =AL54 -> 698.04002 | W54: PPE as % of CapEx | Y54: =G54/G51*-1 -> 0.0018587463 | Z54: =H54/H51*-1 -> 0.00075848187 | AA54: =I54/I51*-1 -> 0.00070504493 | AB54: =J54/J51*-1 -> 0.00070728197 | AC54: =K54/K51*-1 -> 0.00038690917 | AD54: =L54/L51*-1 -> 0.00039363986 | AE54: =M54/M51*-1 -> 0.00024351892 | AF54: =N54/N51*-1 -> 0.0013504956 | AG54: =O54/O51*-1 -> 0.0051687322 | AH54: =P51*AH55*-1 -> 337.0659 | AI54: =Q51*AI55*-1 -> 407.82934 | AJ54: =R51*AJ55*-1 -> 490.12213 | AK54: =S51*AK55*-1 -> 586.06402 | AL54: =T51*AL55*-1 -> 698.04002
B55: Marketable Financial Instruments | G55: 50224 | H55: 44500 | I55: 34426 | J55: 56885 | K55: 53926 | L55: 73744 | M55: 49196 | N55: 41390 | O55: 61305 | P55: 79875 | Q55: 63876 | R55: 46188 | S55: 56609 | T55: 39104 | U55: << | AH55: 0.0009 | AI55: 0.001 | AJ55: 0.0011 | AK55: 0.0012 | AL55: 0.0013
B56: Others | G56: -763 | H56: 6673 | I56: 7446 | J56: 51560 | K56: 32808 | L56: 29749 | M56: 3823 | N56: -4939 | O56: -5375 | P56: =AH49*-1 -> -18726.343 | Q56: =AI49 -> 12642.611 | R56: =AJ49*-1 -> -29557.726 | S56: =AK49*-1 -> -25380.726 | T56: =AL49*-1 -> -35478.187 | W56: Marketable Financial Instruments | Y56: =G55/G52*-1 -> 1.0965939 | Z56: =H55/H52*-1 -> 0.70341274 | AA56: =I55/I52*-1 -> 0.6350606 | AB56: =J55/J52*-1 -> 0.73541389 | AC56: =K55/K52*-1 -> 0.76230192 | AD56: =L55/L52*-1 -> 1.1896304 | AE56: =M55/M52*-1 -> 0.97524036 | AF56: =N55/N52*-1 -> 0.57329252 | AG56: =O55/O52*-1 -> 0.66911516
B57: Net Cash from Investing Activities | G57: -159807 | H57: -197608 | I57: -195509 | J57: -311919 | K57: -290192 | L57: -228489 | M57: -259752 | N57: -365961 | O57: -356854 | P57: =SUM(P48+P49+P51+P52+P54+P55+P56) -> -381554.17 | Q57: =SUM(Q48+Q49+Q51+Q52+Q54+Q55+Q56) -> -373551.79 | R57: =SUM(R48+R49+R51+R52+R54+R55+R56) -> -478664.8 | S57: =SUM(S48+S49+S51+S52+S54+S55+S56) -> -499772.5 | T57: =SUM(T48+T49+T51+T52+T54+T55+T56) -> -548716.55
B59: Cash Flow from Financing Activities
B60: Increase (Decrease) in Hedging Financial Liabilities - Bank Loans | G60: -26496 | H60: 0 | I60: 0 | J60: 0 | K60: 0 | L60: 430 | M60: 0 | N60: -95 | O60: -182 | P60: 0 | Q60: 0 | R60: 0 | S60: 0 | T60: 0 | Z60: =-G52/G55 -> 0.91191462 | AA60: =-H52/H55 -> 1.4216404 | AB60: =-I52/I55 -> 1.5746529 | AC60: =-J52/J55 -> 1.3597785 | AD60: =-K52/K55 -> 1.3118162 | AE60: =-L52/L55 -> 0.8405972 | AF60: =-M52/M55 -> 1.0253882 | AG60: =-N52/N55 -> 1.7443102 | ... AL60: =-S52/S55 -> 1.461764
B61: Proceeds from issuance of Bonds | G61: 22800 | H61: 11500 | I61: 0 | J61: 0 | K61: 19200 | L61: 14100 | M61: 30100 | N61: 23500 | O61: 17200 | P61: =P382 -> 47557 | Q61: =Q382 -> 11590 | R61: =R382 -> 51513.75 | S61: =S382 -> 11115 | T61: =T382 -> 41230 | AD61: Q's | AE61: from Q1 2026 | AH61: from Q4 2025 | AT61: total | AU61: WAI
B62: Repayments of Bonds | G62: 0 | H62: 0 | I62: -5250 | J62: -1750 | K62: -3000 | L62: -10400 | M62: -39160 | N62: -1750 | O62: -4800 | P62: =AA126+AA127 -> -50060 | Q62: =AB126+AB127 -> -12200 | R62: =AC126+AC127 -> -54225 | S62: =AD126+AD127 -> -11700 | T62: =AE126+AE127 -> -43400 | AD62: 46174 | AE62: 0 | AF62: 0 | AG62: 0 | AH62: 5200 | AI62: 0.005 | AJ62: annual | AK62: 6900 | AL62: 0.0052 | AM62: annual | AN62: 3200 | AO62: 0.00535 | AP62: Annual | AQ62: 0 | AR62: 0 | AS62: 0 | AT62: =AE62+AH62+AK62+AN62 -> 15300 | AU62: =((AH62/AT62)*AI62)+((AK62/AT62)*AL62)+((AN62/AT62)*AO62)+((AE62/AT62)*AF62)+((AQ62/AT62)*AR62) -> 0.0051633987
B63: Proceeds from Long Term bank Loans | G63: 6378 | H63: 0 | I63: 17064 | J63: 7455 | K63: 5395 | L63: 0 | M63: 2232 | N63: 3031 | O63: 2020 | P63: 0 | Q63: 0 | R63: 0 | S63: 0 | T63: 0 | U63: << | W63: Due to Lack of Data on repaymant of bank loans have assumed refinancing equals to repayment | AD63: 46266 | AE63: =1100*31.59 -> 34749 | AF63: 0.02515625 | AG63: Annual | AH63: 8000 | AI63: 0.005 | AJ63: annual | AK63: 1200 | AL63: 0.016 | AM63: annual | AN63: 3000 | AO63: 0.0084 | AP63: Annual | AQ63: 0 | AR63: 0 | AS63: 0 | AT63: =AE63+AH63+AK63+AN63 -> 46949 | AU63: =((AH63/AT63)*AI63)+((AK63/AT63)*AL63)+((AN63/AT63)*AO63)+((AE63/AT63)*AF63)+((AQ63/AT63)*AR63) -> 0.020416932
B64: Repayments of Long Term Bank Loans | G64: -513 | H64: -543 | I64: -604 | J64: -636 | K64: -719 | L64: -719 | M64: -720 | N64: -552 | O64: -390 | P64: 0 | Q64: 0 | R64: 0 | S64: 0 | T64: 0 | U64: << | AD64: 46357 | AE64: =1250*31.59 -> 39487.5 | AF64: 0.03530625 | AG64: Annual | AH64: 6900 | AI64: 0.0054 | AJ64: annual | AK64: 7700 | AL64: 0.0065 | AM64: annual | AN64: 0 | AO64: 0 | AP64: 0 | AQ64: 0 | AR64: 0 | AS64: 0 | AT64: =AE64+AH64+AK64+AN64 -> 54087.5 | AU64: =((AH64/AT64)*AI64)+((AK64/AT64)*AL64)+((AN64/AT64)*AO64)+((AE64/AT64)*AF64)+((AQ64/AT64)*AR64) -> 0.027390165
B65: Interest paid | G65: -1779 | H65: -6641 | I65: -4385 | J65: -5946 | K65: -2516 | L65: -7223 | M65: -4040 | N65: -5350 | O65: -2747 | P65: =P423 -> -5357.6054 | Q65: =Q423 -> -5348.2664 | R65: =R423 -> -5338.3026 | S65: =S423 -> -5328.4139 | T65: =T423 -> -6172.6806 | AD65: 46447 | AE65: 0 | AF65: 0 | AG65: 0 | AH65: 10500 | AI65: 0.0062 | AJ65: annual | AK65: 2100 | AL65: 0.0063 | AM65: annual | AN65: 9600 | AO65: 0.0085 | AP65: Annual | AQ65: 0 | AR65: 0 | AS65: 0 | AT65: =AE65+AH65+AK65+AN65 -> 22200 | AU65: =((AH65/AT65)*AI65)+((AK65/AT65)*AL65)+((AN65/AT65)*AO65)+((AE65/AT65)*AF65)+((AQ65/AT65)*AR65) -> 0.0072040541
B66: Cash Dividends Paid for Common Stock | G66: -77796 | H66: -90762 | I66: -90763 | J66: -103734 | K66: -103722 | L66: -116697 | M66: -116697 | N66: -129663 | O66: -129663 | P66: =P438*-1 -> -146026.5 | Q66: =Q438*-1 -> -161420.29 | R66: =R438*-1 -> -178680.93 | S66: =S438*-1 -> -198235.02 | T66: =T438*-1 -> -220285.32 | AD66: 46539 | AE66: =1000*31.59 -> 31590 | AF66: 0.079001563 | AG66: Annual | AH66: 10400 | AI66: 0.0058 | AJ66: annual | AK66: 7500 | AL66: 0.006 | AM66: annual | AN66: 2000 | AO66: 0.0165 | AP66: Annual | AQ66: 6100 | AR66: 0.015 | AS66: annual | AT66: =AE66+AH66+AK66+AN66 -> 51490 | AU66: =((AH66/AT66)*AI66)+((AK66/AT66)*AL66)+((AN66/AT66)*AO66)+((AE66/AT66)*AF66)+((AQ66/AT66)*AR66) -> 0.052932207
B67: Repurchases of Tresury Stock | G67: 0 | H67: -3089 | I67: 0 | J67: 0 | K67: 0 | L67: 0 | M67: 0 | N67: 0 | O67: 0 | P67: 0 | Q67: 0 | R67: 0 | S67: 0 | T67: 0 | AT67: =SUM(AT62:AT66) -> 190026.5
B68: others | G68: 5721 | H68: -710 | I68: 299 | J68: 3879 | K68: 696 | L68: 809 | M68: -9 | N68: 3194 | O68: -1348 | P68: -1348 | Q68: -1348 | R68: -1348 | S68: -1348 | T68: -1348 | U68: << | W68: Kept it as same as previous quarter as it fluctuautes to much | AE68: 1100 | AF68: 0.0125 | AG68: semi annual | AH68: =AE68 -> 1100 | AI68: =((1+AF68)^2)-1 -> 0.02515625 | AJ68: Annual | AT68: =((AT62/AT67)*AU62)+((AT63/AT67)*AU63)+((AT64/AT67)*AU64)+((AT65/AT67)*AU65)+((AT66/AT67)*AU66) -> 0.028440399 | AU68: =AT68/4 -> 0.0071100997
B69: Net Cash from Financing Activities | G69: -71685 | H69: -90245 | I69: -83639 | J69: -100732 | K69: -84666 | L69: -119700 | M69: -128294 | N69: -107685 | O69: -119910 | P69: =SUM(P60:P68) -> -155235.1 | Q69: =SUM(Q60:Q68) -> -168726.56 | R69: =SUM(R60:R68) -> -188078.48 | S69: =SUM(S60:S68) -> -205496.43 | T69: =SUM(T60:T68) -> -229976 | AE69: 1250 | AF69: 0.0175 | AG69: semi annual | AH69: =AE69 -> 1250 | AI69: =((1+AF69)^2)-1 -> 0.03530625 | AJ69: Annual | AT69: =((AT63/$AT$67)*AU63)+((AT64/$AT$67)*AU64)+((AT65/$AT$67)*AU65)+((AT66/$AT$67)*AU66) -> 0.028024667 | AU69: =AT69/4 -> 0.0070061668
AE70: 0 | AF70: 0 | AG70: 0 | AH70: 0 | AI70: 0 | AJ70: 0 | AT70: =((AT64/$AT$67)*AU64)+((AT65/$AT$67)*AU65)+((AT66/$AT$67)*AU66)+((AT67/$AT$67)*AU67) -> 0.022980347 | AU70: =AT70/4 -> 0.0057450867
B71: Effect of Exchange Rate Changes | G71: 27949 | H71: 11116 | I71: -25191 | J71: 33292 | K71: 16461 | L71: -179155 | M71: 67452 | N71: 45234 | O71: 45569 | P71: 0 | Q71: 0 | R71: 0 | S71: 0 | T71: 0 | U71: << | V71: =MEDIAN(G71:O71) -> 27949 | AE71: 1000 | AF71: 0.03875 | AG71: semi annual | AH71: =AE71 -> 1000 | AI71: =((1+AF71)^2)-1 -> 0.079001563 | AJ71: Annual | AT71: =((AT65/$AT$67)*AU65)+((AT66/$AT$67)*AU66)+((AT67/$AT$67)*AU67)+((AT68/$AT$67)*AU68) -> 0.015184248 | AU71: =AT71/4 -> 0.0037960621
V72: =V71/O71 -> 0.61333363 | AT72: =((AT66/$AT$67)*AU66)+((AT67/$AT$67)*AU67)+((AT68/$AT$67)*AU68)+((AT69/$AT$67)*AU69) -> 0.01434263 | AU72: =AT72/4 -> 0.0035856575
B73: net Increase in Cash and Cash Equivalents | G73: 232768 | H73: 100931 | I73: 87654 | J73: 240846 | K73: 267177 | L73: -30280 | M73: 106235 | N73: 297097 | O73: 267781 | P73: =P45+P57+P69+P71 -> 354180.46 | Q73: =Q45+Q57+Q69+Q71 -> 400459.13 | R73: =R45+R57+R69+R71 -> 377226.33 | S73: =S45+S57+S69+S71 -> 457496.16 | T73: =T45+T57+T69+T71 -> 533951.5
B75: Cash and Cash Equivalents at Beginning of Period | G75: 1465428 | H75: 1698196 | I75: 1799127 | J75: 1886781 | K75: 2127627 | L75: 2394804 | M75: 2364524 | N75: 2470759 | O75: 2767856 | P75: =O76 -> 3035637 | Q75: =P76 -> 3389817.5 | R75: =Q76 -> 3790276.6 | S75: =R76 -> 4167502.9 | T75: =S76 -> 4624999.1
B76: Cash and Cash Equivalents at End od Period | G76: 1698196 | H76: 1799127 | I76: 1886781 | J76: 2127627 | K76: 2394804 | L76: 2364524 | M76: 2470759 | N76: 2767856 | O76: 3035637 | P76: =P73+P75 -> 3389817.5 | Q76: =Q73+Q75 -> 3790276.6 | R76: =R73+R75 -> 4167502.9 | S76: =S73+S75 -> 4624999.1 | T76: =T73+T75 -> 5158950.6
B79: Balance Sheet
B80: all figures in millions of New Taiwan Dollors NTD | G80: =G2 -> 45382 | H80: =H2 -> 45473 | I80: =I2 -> 45565 | J80: =J2 -> 45656 | K80: =K2 -> 45746 | L80: =L2 -> 45838 | M80: =M2 -> 45930 | N80: =N2 -> 46021 | ... U80: =U2 -> Term
B82: Current Assets
B83: Cash and Cash equivalents | G83: 1698196 | H83: 1799127 | I83: 1886781 | J83: 2127627 | K83: 2394804 | L83: 2364524 | M83: 2470759 | N83: 2767856 | O83: 3035637 | P83: =P76 -> 3389817.5 | Q83: =Q76 -> 3790276.6 | R83: =R76 -> 4167502.9 | S83: =S76 -> 4624999.1 | T83: =T76 -> 5158950.6
B84: Investment in Marketable Financial instruments | G84: 224460 | H84: 249508 | I84: 280819 | J84: 294392 | K84: 308281 | L84: 269905 | M84: 280297 | N84: 300738 | O84: 347964 | P84: =AH84 -> 372879.92 | Q84: =AI84 -> 407454.73 | R84: =AJ84 -> 427169.05 | S84: =AK84 -> 462499.91 | T84: =AL84 -> 502997.68 | W84: Investments in Marketable Fin Instruments | Y84: =G84/G83 -> 0.13217556 | Z84: =H84/H83 -> 0.13868282 | AA84: =I84/I83 -> 0.14883497 | AB84: =J84/J83 -> 0.13836636 | AC84: =K84/K83 -> 0.12872912 | AD84: =L84/L83 -> 0.11414771 | AE84: =M84/M83 -> 0.11344571 | AF84: =N84/N83 -> 0.10865377 | AG84: =O84/O83 -> 0.11462635 | AH84: =AH85*P83 -> 372879.92 | AI84: =AI85*Q83 -> 407454.73 | AJ84: =AJ85*R83 -> 427169.05 | AK84: =AK85*S83 -> 462499.91 | AL84: =AL85*T83 -> 502997.68
B85: Accounts Receivables | G85: 201980 | H85: 210210 | I85: 249974 | J85: 272088 | K85: 243949 | L85: 235685 | M85: 307814 | N85: 281791 | O85: 363005 | P85: =P196 -> 383337.83 | Q85: =Q196 -> 432022.61 | R85: =R196 -> 481190.56 | S85: =S196 -> 533131.67 | T85: =T196 -> 578434.39 | W85: as % of Cash and equivalents | AH85: 0.11 | AI85: 0.1075 | AJ85: 0.1025 | AK85: 0.1 | AL85: 0.0975
B86: Inventories | G86: 267123 | H86: 272491 | I86: 292884 | J86: 287869 | K86: 293388 | L86: 304194 | M86: 288689 | N86: 288110 | O86: 311454 | P86: =P197 -> 328432.32 | Q86: =Q197 -> 362241.56 | R86: =R197 -> 406732.65 | S86: =S197 -> 455208.76 | T86: =T197 -> 487760.89
B87: Other Current Assets | G87: 61008 | H87: 60332 | I87: 63456 | J87: 106376 | K87: 105242 | L87: 90610 | M87: 88456 | N87: 178636 | O87: 207452 | P87: =AH87 -> 212226.68 | Q87: =AI87 -> 238476.48 | R87: =AJ87 -> 268875.78 | S87: =AK87 -> 304170.66 | T87: =AL87 -> 345184.63 | W87: Other Current Assets as % of Rev | Y87: =G87/G4 -> 0.10294207 | Z87: =H87/H4 -> 0.089578477 | AA87: =I87/I4 -> 0.083528588 | AB87: =J87/J4 -> 0.12248794 | AC87: =K87/K4 -> 0.12539946 | AD87: =L87/L4 -> 0.097034457 | AE87: =M87/M4 -> 0.089356896 | AF87: =N87/N4 -> 0.17076542 | AG87: =O87/O4 -> 0.18292166 | AH87: =AH88*P4 -> 212226.68 | AI87: =AI88*Q4 -> 238476.48 | AJ87: =AJ88*R4 -> 268875.78 | AK87: =AK88*S4 -> 304170.66 | AL87: =AL88*T4 -> 345184.63
B88: Total Current Assets | G88: 2452767 | H88: 2591658 | I88: 2773914 | J88: 3088352 | K88: 3345664 | L88: 3264918 | M88: 3436015 | N88: 3817131 | O88: 4265512 | P88: =SUM(P83:P87) -> 4686694.2 | Q88: =SUM(Q83:Q87) -> 5230472 | R88: =SUM(R83:R87) -> 5751471 | S88: =SUM(S83:S87) -> 6380010.1 | T88: =SUM(T83:T87) -> 7073328.2 | AH88: 0.17 | AI88: 0.1725 | AJ88: 0.175 | AK88: 0.1775 | AL88: 0.18
B90: Non Current Assets
B91: Long term investments | G91: 138469 | H91: 140220 | I91: 127332 | J91: 149040 | K91: 160793 | L91: 137427 | M91: 148978 | N91: 172370 | O91: 166567 | P91: =AH91 -> 181016.87 | Q91: =AI91 -> 186633.77 | R91: =AJ91 -> 192054.13 | S91: =AK91 -> 205636.5 | T91: =AL91 -> 230123.09 | W91: Long Term Investment as % of Rev | Y91: =G91/G4 -> 0.23364617 | Z91: =H91/H4 -> 0.2081929 | AA91: =I91/I4 -> 0.16761003 | AB91: =J91/J4 -> 0.17161392 | AC91: =K91/K4 -> 0.19159039 | AD91: =L91/L4 -> 0.14717089 | AE91: =M91/M4 -> 0.15049529 | AF91: =N91/N4 -> 0.1647755 | AG91: =O91/O4 -> 0.14687114 | AH91: =AH92*P4 -> 181016.87 | AI91: =AI92*Q4 -> 186633.77 | AJ91: =AJ92*R4 -> 192054.13 | AK91: =AK92*S4 -> 205636.5 | AL91: =AL92*T4 -> 230123.09
B92: PPE | G92: 3051848 | H92: 3105860 | I92: 3071599 | J92: 3234980 | K92: 3400806 | L92: 3386206 | M92: 3499341 | N92: 3691841 | O92: 3954679 | P92: =P264 -> 4152500.4 | Q92: =Q264 -> 4375137.1 | R92: =R264 -> 4626227.3 | S92: =S264 -> 4909964 | T92: =T264 -> 5231081.3 | AH92: 0.145 | AI92: 0.135 | AJ92: 0.125 | AK92: 0.12 | AL92: 0.12
B93: ROU, Intangible and Other Non Current Assets | G93: 144807 | H93: 144626 | I93: 192813 | J93: 219566 | K93: 226024 | L93: 217799 | M93: 269773 | N93: 251682 | O93: 274192 | P93: =AH93 -> 303359.31 | Q93: =AI93 -> 336632.01 | R93: =AJ93 -> 372585 | S93: =AK93 -> 414700.27 | T93: =AL93 -> 461205.02 | W93: ROU, Intangible & ONC Assets % Rev | Y93: =G93/G4 -> 0.24434062 | Z93: =H93/H4 -> 0.21473475 | AA93: =I93/I4 -> 0.25380417 | AB93: =J93/J4 -> 0.25282195 | AC93: =K93/K4 -> 0.26931537 | AD93: =L93/L4 -> 0.23324145 | AE93: =M93/M4 -> 0.27252055 | AF93: =N93/N4 -> 0.24059307 | AG93: =O93/O4 -> 0.24176993 | AH93: =AH94*P4 -> 303359.31 | AI93: =AI94*Q4 -> 336632.01 | AJ93: =AJ94*R4 -> 372585 | AK93: =AK94*S4 -> 414700.27 | AL93: =AL94*T4 -> 461205.02
B94: Total Non Current Assets | G94: 3335124 | H94: 3390706 | I94: 3391744 | J94: 3603586 | K94: 3787623 | L94: 3741432 | M94: 3918092 | N94: 4115893 | O94: 4395438 | P94: =SUM(P91:P93) -> 4636876.6 | Q94: =SUM(Q91:Q93) -> 4898402.8 | R94: =SUM(R91:R93) -> 5190866.5 | S94: =SUM(S91:S93) -> 5530300.8 | T94: =SUM(T91:T93) -> 5922409.4 | AH94: 0.243 | AI94: 0.2435 | AJ94: 0.2425 | AK94: 0.242 | AL94: 0.2405
B96: Total Assets | G96: 5787891 | H96: 5982364 | I96: 6165658 | J96: 6691938 | K96: 7133287 | L96: 7006350 | M96: 7354107 | N96: 7933024 | O96: 8660950 | P96: =P88+P94 -> 9323570.8 | Q96: =Q88+Q94 -> 10128875 | R96: =R88+R94 -> 10942337 | S96: =S88+S94 -> 11910311 | T96: =T88+T94 -> 12995738
W98: Payables to Contractors and equipment suppliers | Y98: =G101 -> 127179 | Z98: =H101 -> 136744 | AA98: =I101 -> 125132 | AB98: =J101 -> 192635 | AC98: =K101 -> 199087 | AD98: =L101 -> 161416 | AE98: =M101 -> 175430 | AF98: =N101 -> 177730 | AG98: =O101 -> 243927 | AH98: =(AH100/365)*AH99 -> 260623.25 | AI98: =(AI100/365)*AI99 -> 280452.5 | AJ98: =(AJ100/365)*AJ99 -> 302740.44 | AK98: =(AK100/365)*AK99 -> 327821.2 | AL98: =(AL100/365)*AL99 -> 356007.77
B99: Current liabilities | W99: drivers COGS and CapEx | Y99: =(G5+G51)*-1 -> 459444 | Z99: =(H5+H51)*-1 -> 521059 | AA99: =(I5+I51)*-1 -> 527426 | AB99: =(J5+J51)*-1 -> 718031 | AC99: =(K5+K51)*-1 -> 676686 | AD99: =(L5+L51)*-1 -> 683649 | AE99: =(M5+M51)*-1 -> 688827 | AF99: =(N5+N51)*-1 -> 751009 | ... AL99: =(T5+T51)*-1 -> 1160203.9
B100: Account Payable | G100: 57610 | H100: 63947 | I100: 70820 | J100: 74227 | K100: 76854 | L100: 84772 | M100: 86386 | N100: 84330 | O100: 99856 | P100: =P198 -> 103416.41 | Q100: =Q198 -> 114918.01 | R100: =R198 -> 130934.48 | S100: =S198 -> 149657.67 | T100: =T198 -> 155812.51 | W100: Days Payable Outstanding | Y100: =(Y98/Y99)*365 -> 101.03589 | Z100: =(Z98/Z99)*365 -> 95.788692 | AA100: =(AA98/AA99)*365 -> 86.596376 | AB100: =(AB98/AB99)*365 -> 97.923035 | AC100: =(AC98/AC99)*365 -> 107.38622 | AD100: =(AD98/AD99)*365 -> 86.179955 | AE100: =(AE98/AE99)*365 -> 92.957956 | AF100: =(AF98/AF99)*365 -> 86.379058 | AG100: =(AG98/AG99)*365 -> 121.36979 | AH100: 120 | AI100: 118 | AJ100: 116 | AK100: 114 | AL100: 112
B101: paybles to Contractors and Equipment Suppliers | G101: 127179 | H101: 136744 | I101: 125132 | J101: 192635 | K101: 199087 | L101: 161416 | M101: 175430 | N101: 177730 | O101: 243927 | P101: =AH98 -> 260623.25 | Q101: =AI98 -> 280452.5 | R101: =AJ98 -> 302740.44 | S101: =AK98 -> 327821.2 | T101: =AL98 -> 356007.77
B102: Cash Dividends Payable | G102: 181525 | H102: 194600 | I102: 207456 | J102: 220419 | K102: 233394 | L102: 246672 | M102: 259326 | N102: 285258 | O102: 311190 | P102: =AJ146 -> 346673.5 | Q102: =AK146 -> 379728.21 | R102: =AL146 -> 408487.29 | S102: =AM146 -> 430657.27 | T102: =AN146 -> 443741.95
B103: Accrued Expenses and Other Current Liabilities | G103: 647366 | H103: 630549 | I103: 618186 | J103: 717386 | K103: 828696 | L103: 790240 | M103: 678538 | N103: 773775 | O103: 903039 | P103: =AH103 -> 964989.58 | Q103: =AI103 -> 1033145.2 | R103: =AJ103 -> 1121589.6 | S103: =AK103 -> 1238672.3 | T103: =AL103 -> 1358054.6 | W103: Accrued Expenses and Other Current Liabilities | Y103: =G103/G96 -> 0.11184834 | Z103: =H103/H96 -> 0.10540131 | AA103: =I103/I96 -> 0.10026278 | AB103: =J103/J96 -> 0.10720153 | AC103: =K103/K96 -> 0.11617309 | AD103: =L103/L96 -> 0.11278911 | AE103: =M103/M96 -> 0.092266539 | AF103: =N103/N96 -> 0.097538467 | AG103: =O103/O96 -> 0.10426558 | AH103: =AH104*P96 -> 964989.58 | AI103: =AI104*Q96 -> 1033145.2 | AJ103: =AJ104*R96 -> 1121589.6 | AK103: =AK104*S96 -> 1238672.3 | AL103: =AL104*T96 -> 1358054.6
B104: Current Portion of Bonds Payable and Bank loans | G104: 12500 | H104: 23076 | I104: 58805 | J104: 59858 | K104: 61772 | L104: 94214 | M104: 76226 | N104: 136926 | O104: 156242 | P104: =AH111 -> 168042.32 | Q104: =AI111 -> 225712.32 | R104: =AJ111 -> 192987.32 | S104: =AK111 -> 204887.32 | T104: =AL111 -> 202287.32 | W104: As % of Total Assets | AH104: 0.1035 | AI104: 0.102 | AJ104: 0.1025 | AK104: 0.104 | AL104: 0.1045
B105: Total Current Liabilities | G105: 1026180 | H105: 1048916 | I105: 1080399 | J105: 1264525 | K105: 1399803 | L105: 1377314 | M105: 1275906 | N105: 1458019 | O105: 1714254 | P105: =SUM(P100:P104) -> 1843745.1 | Q105: =SUM(Q100:Q104) -> 2033956.3 | R105: =SUM(R100:R104) -> 2156739.1 | S105: =SUM(S100:S104) -> 2351695.8 | T105: =SUM(T100:T104) -> 2515904.1
Z106: =(H103/(H4+G4)) -> 0.4980034 | AA106: =(I103/(I4+H4)) -> 0.43133208 | AB106: =(J103/(J4+I4)) -> 0.44061338 | AC106: =(K103/(K4+J4)) -> 0.48526598 | AD106: =(L103/(L4+K4)) -> 0.44569628 | AE106: =(M103/(M4+L4)) -> 0.35272364 | AF106: =(N103/(N4+M4)) -> 0.38004517 | AG106: =(O103/(O4+N4)) -> 0.4142014 | AH106: =AH107*(O4+P4) -> 970866.81 | AI106: =AI107*(P4+Q4) -> 1058923 | AJ106: =AJ107*(Q4+R4) -> 1179237.8 | AK106: =AK107*(R4+S4) -> 1332528.9 | AL106: =AL107*(S4+T4) -> 1488845.2
B107: Non Current Liabilities | AH107: 0.4075 | AI107: 0.4025 | AJ107: 0.404 | AK107: 0.41 | AL107: 0.41
B108: Bonds Payable | G108: 955540 | H108: 965314 | I108: 909704 | J108: 926604 | K108: 948257 | L108: 848535 | M108: 880433 | N108: 856228 | O108: 860026 | P108: =P383 -> 857523 | Q108: =P108*(1+5%) -> 900399.15 | R108: =Q108*(1+5%) -> 945419.11 | S108: =R108*(1+5%)+(39047.0013286322/2) -> 1012213.6 | T108: =S108*(1+5%)+(39047.0013286322/2) -> 1082347.7 | W108: Current Portions and ONCL
B109: Bank Loans | P109: =P391 -> 40991.672 | Q109: =Q391 -> 40991.672 | R109: =R391 -> 40991.672 | S109: =S391 -> 40991.672 | T109: =T391 -> 40991.672 | X109: Current Portion of the Bonds Payable | Y109: =Y115 -> 9997.778 | Z109: =Z115 -> 20397.667 | AA109: =AA115 -> 56011.666 | AB109: =AB115 -> 57148 | AC109: =AC115 -> 59391.445 | AD109: =AD115 -> 92290.945 | AE109: =AE115 -> 74760.444 | AF109: =AF115 -> 135806.28 | AG109: =AG115 -> 154676.32 | AH109: =AA129 -> 165916.32 | AI109: =AB129 -> 223586.32 | AJ109: =AC129 -> 190861.32 | AK109: =AD129 -> 202761.32 | AL109: =AE129 -> 200161.32
B110: Other Non Current Liabilities | G110: 140455 | H110: 147986 | I110: 153633 | J110: 177233 | K110: 183603 | L110: 163869 | M110: 132190 | N110: 157982 | O110: 154281 | P110: =AH143 -> 118597.26 | Q110: =AI143 -> 127878.69 | R110: =AJ143 -> 138278.97 | S110: =AK143 -> 154227.37 | T110: =AL143 -> 172592.31 | X110: Current Portion of the Bank Loans | Y110: =Y120 -> 2502.222 | Z110: =Z120 -> 2678.333 | AA110: =AA120 -> 2793.334 | AB110: =AB120 -> 2710 | AC110: =AC120 -> 2380.555 | AD110: =AD120 -> 1923.055 | AE110: =AE120 -> 1465.556 | AF110: =AF120 -> 1119.722 | AG110: =AG120 -> 1565.417 | AH110: 2126 | AI110: 2126 | AJ110: 2126 | AK110: 2126 | AL110: 2126
B111: Total Non Current Liabilities | G111: 1095995 | H111: 1113300 | I111: 1063337 | J111: 1103837 | K111: 1131860 | L111: 1012404 | M111: 1042623 | N111: 1014210 | O111: 1014307 | P111: =SUM(P108:P110) -> 1017111.9 | Q111: =SUM(Q108:Q110) -> 1069269.5 | R111: =SUM(R108:R110) -> 1124689.8 | S111: =SUM(S108:S110) -> 1207432.6 | T111: =SUM(T108:T110) -> 1295931.7 | X111: Current Portion of the Bonds and Bank Loans | Y111: =SUM(Y109:Y110) -> 12500 | Z111: =SUM(Z109:Z110) -> 23076 | AA111: =SUM(AA109:AA110) -> 58805 | AB111: =SUM(AB109:AB110) -> 59858 | AC111: =SUM(AC109:AC110) -> 61772 | AD111: =SUM(AD109:AD110) -> 94214 | AE111: =SUM(AE109:AE110) -> 76226 | AF111: =SUM(AF109:AF110) -> 136926 | ... AL111: =SUM(AL109:AL110) -> 202287.32 | AM111: average of previous quarters
B113: Total Liabilities | G113: 2122175 | H113: 2162216 | I113: 2143736 | J113: 2368362 | K113: 2531663 | L113: 2389718 | M113: 2318529 | N113: 2472229 | O113: 2728561 | P113: =P111+P105 -> 2860857 | Q113: =Q111+Q105 -> 3103225.8 | R113: =R111+R105 -> 3281428.9 | S113: =S111+S105 -> 3559128.4 | T113: =T111+T105 -> 3811835.8 | X113: Bonds:
X114: Bonds Payable | Y114: 955540 | Z114: 965314 | AA114: 909704 | AB114: 926604 | AC114: 948257 | AD114: 848535 | AE114: 880433 | AF114: 856228 | AG114: 860026
B115: Equity Attributable to the Shareholders of Parent | X115: Current Bond | Y115: 9997.778 | Z115: 20397.667 | AA115: 56011.666 | AB115: 57148 | AC115: 59391.445 | AD115: 92290.945 | AE115: 74760.444 | AF115: 135806.28 | AG115: 154676.32
B116: Capital Stock at Par | G116: 259336 | H116: 259336 | I116: 259327 | J116: 259327 | K116: 259326 | L116: 259326 | M116: 259325 | N116: 259325 | O116: 259324 | P116: 259324 | Q116: 259324 | R116: 259324 | S116: 259324 | T116: 259324 | X116: Repayments | Y116: 0 | Z116: 0 | AA116: -5250 | AB116: -1750 | AC116: -3000 | AD116: -10400 | AE116: -39160 | AF116: -1750 | AG116: -4800
B117: Capital Surplus | G117: 70941 | H117: 70941 | I117: 72390 | J117: 73261 | K117: 73307 | L117: 73326 | M117: 73361 | N117: 73446 | O117: 73666 | P117: 73666 | Q117: 73666 | R117: 73666 | S117: 73666 | T117: 73666
B118: Legal Capital Reserve | G118: 311147 | H118: 311147 | I118: 311147 | J118: 311147 | K118: 311147 | L118: 311147 | M118: 311147 | N118: 311147 | O118: 311147 | P118: =P449 -> 311147 | Q118: =Q449 -> 311147 | R118: =R449 -> 311147 | S118: =S449 -> 311147 | T118: =T449 -> 311147 | X118: Bank Loans:
B119: Special Capital Reserve | G119: 28021 | H119: 0 | I119: 0 | J119: 0 | K119: 0 | L119: 0 | M119: 181555 | N119: 87284 | O119: 16199 | P119: =P451 -> 57652.5 | Q119: =Q451 -> 72468.25 | R119: =R451 -> 72468.25 | S119: =S451 -> 72468.25 | T119: =T451 -> 72468.25 | X119: Loans | Y119: 10020.132 | Z119: 9029.765 | AA119: 26459.677 | AB119: 31824.386 | AC119: 38726.925 | AD119: 35136 | AE119: 37795.501 | AF119: 39834.496 | AG119: 40991.672
B120: Unappropriated Earnings | G120: 2955396 | H120: 3127528 | I120: 3346232 | J120: 3606105 | K120: 3851130 | L120: 4119741 | M120: 4260829 | N120: 4705070 | O120: 5193142 | P120: =P447 -> 5682013.3 | Q120: =Q447 -> 6230132.8 | R120: =R447 -> 6845589.3 | S120: =S447 -> 7538298.2 | T120: =T447+76597.3814762644/2 -> 8357608.4 | X120: Current Bank Loan | Y120: 2502.222 | Z120: 2678.333 | AA120: 2793.334 | AB120: 2710 | AC120: 2380.555 | AD120: 1923.055 | AE120: 1465.556 | AF120: 1119.722 | AG120: 1565.417
B121: Treasury Stock | G121: 0 | H121: -3089 | I121: 0 | J121: 0 | K121: 0 | L121: 0 | M121: 0 | N121: 0 | O121: 0 | P121: 0 | Q121: 0 | R121: 0 | S121: 0 | T121: 0 | X121: Repayment | Y121: -513 | Z121: -543 | AA121: -604 | AB121: -636 | AC121: -719 | AD121: -719 | AE121: -720 | AF121: -552 | AG121: -390
...

Sheet Key Ratios & Metrics
B2: Profitability and Return Ratios | E2: Note: All The Ratios In Bold Are Relevant & Important For The Analysis
B3: all figures in millions of New Taiwan Dollors NTD
F4: =Historicals!C2 -> 45352 | G4: =Historicals!D2 -> 45473 | H4: =Historicals!E2 -> 45565 | I4: =Historicals!F2 -> 45657 | J4: =Historicals!G2 -> 45747 | K4: =Historicals!H2 -> 45838 | L4: =Historicals!I2 -> 45930 | M4: =Historicals!J2 -> 46022 | N4: =Historicals!K2 -> 46112 | P4: =F4 -> 45352 | Q4: =G4 -> 45473 | R4: =H4 -> 45565 | S4: =I4 -> 45657 | T4: =J4 -> 45747 | U4: =K4 -> 45838 | V4: =L4 -> 45930 | W4: =M4 -> 46022 | X4: =N4 -> 46112
B7: Return on Equity | C7: = | D7: Net Income | E7: = | F7: =Historicals!C27 -> 225221 | G7: =Historicals!D27 -> 247662 | H7: =Historicals!E27 -> 325080 | I7: =Historicals!F27 -> 374469 | J7: =Historicals!G27 -> 360733 | K7: =Historicals!H27 -> 397493 | L7: =Historicals!I27 -> 451755 | M7: =Historicals!J27 -> 505416 | N7: =Historicals!K27 -> 572480 | O7: = | P7: =IF(F8=0,,F7/F8) -> 0.061946535 | Q7: =IF(G8=0,,G7/G8) -> 0.065321993 | R7: =IF(H8=0,,H7/H8) -> 0.081473296 | S7: =IF(I8=0,,I7/I8) -> 0.087318426 | T7: =IF(J8=0,,J7/J8) -> 0.079035976 | U7: =IF(K8=0,,K7/K8) -> 0.086768518 | V7: =IF(L8=0,,L7/L8) -> 0.090381603 | W7: =IF(M8=0,,M7/M8) -> 0.093257136 | X7: =IF(N8=0,,N7/N8) -> 0.097179407
D8: Equity | F8: =Historicals!C122 -> 3635732 | G8: =Historicals!D122 -> 3791403 | H8: =Historicals!E122 -> 3990019 | I8: =Historicals!F122 -> 4288545 | J8: =Historicals!G122 -> 4564162 | K8: =Historicals!H122 -> 4581074 | L8: =Historicals!I122 -> 4998307 | M8: =Historicals!J122 -> 5419596 | N8: =Historicals!K122 -> 5890960
B10: Return on Assets | C10: = | D10: Net Income | E10: = | F10: =+F7 -> 225221 | G10: =+G7 -> 247662 | H10: =+H7 -> 325080 | I10: =+I7 -> 374469 | J10: =+J7 -> 360733 | K10: =+K7 -> 397493 | L10: =+L7 -> 451755 | M10: =+M7 -> 505416 | N10: =+N7 -> 572480 | O10: = | P10: =IF(F11=0,,F10/F11) -> 0.038912447 | Q10: =IF(G11=0,,G10/G11) -> 0.041398685 | R10: =IF(H11=0,,H10/H11) -> 0.0527243 | S10: =IF(I11=0,,I10/I11) -> 0.055958229 | T10: =IF(J11=0,,J10/J11) -> 0.050570375 | U10: =IF(K11=0,,K10/K11) -> 0.056733249 | V10: =IF(L11=0,,L10/L11) -> 0.06142894 | W10: =IF(M11=0,,M10/M11) -> 0.063710383 | X10: =IF(N11=0,,N10/N11) -> 0.066098985
D11: Total Assets | F11: =Historicals!C96 -> 5787891 | G11: =Historicals!D96 -> 5982364 | H11: =Historicals!E96 -> 6165658 | I11: =Historicals!F96 -> 6691938 | J11: =Historicals!G96 -> 7133287 | K11: =Historicals!H96 -> 7006350 | L11: =Historicals!I96 -> 7354107 | M11: =Historicals!J96 -> 7933024 | N11: =Historicals!K96 -> 8660950
B13: Return on Net Assets | C13: = | D13: Net Income | E13: = | F13: =F10 -> 225221 | G13: =G10 -> 247662 | H13: =H10 -> 325080 | I13: =I10 -> 374469 | J13: =J10 -> 360733 | K13: =K10 -> 397493 | L13: =L10 -> 451755 | M13: =M10 -> 505416 | N13: =N10 -> 572480 | O13: = | P13: =IF(F14=0,,F13/F14) -> 0.05767642 | Q13: =IF(G14=0,,G13/G14) -> 0.062186852 | R13: =IF(H14=0,,H13/H14) -> 0.079619391 | S13: =IF(I14=0,,I13/I14) -> 0.087137509 | T13: =IF(J14=0,,J13/J14) -> 0.080835766 | U13: =IF(K14=0,,K13/K14) -> 0.090428966 | V13: =IF(L14=0,,L13/L14) -> 0.097750053 | W13: =IF(M14=0,,M13/M14) -> 0.10308074 | X13: =IF(N14=0,,N13/N14) -> 0.10839283
D14: PP&E plus Net Working Capital | F14: =Historicals!C153 -> 3904906 | G14: =Historicals!D153 -> 3982546 | H14: =Historicals!E153 -> 4082925 | I14: =Historicals!F153 -> 4297449 | J14: =Historicals!G153 -> 4462542 | K14: =Historicals!H153 -> 4395638 | L14: =Historicals!I153 -> 4621532 | M14: =Historicals!J153 -> 4903108 | N14: =Historicals!K153 -> 5281530
B16: Return on Invested Capital | C16: = | D16: NOPAT | E16: = | F16: =Historicals!C137 -> 210412.89 | G16: =Historicals!D137 -> 231689.47 | H16: =Historicals!E137 -> 305262.31 | I16: =Historicals!F137 -> 355207.29 | J16: =Historicals!G137 -> 340796.6 | K16: =Historicals!H137 -> 373618.56 | L16: =Historicals!I137 -> 430529.69 | M16: =Historicals!J137 -> 481986.58 | N16: =Historicals!K137 -> 548788 | O16: = | P16: =IF(F17=0,,F16/F17) -> 0.071433429 | Q16: =IF(G17=0,,G16/G17) -> 0.076757997 | R16: =IF(H17=0,,H16/H17) -> 0.097524477 | S16: =IF(I17=0,,I16/I17) -> 0.11051067 | T16: =IF(J17=0,,J16/J17) -> 0.10468089 | U16: =IF(K17=0,,K16/K17) -> 0.11567163 | V16: =IF(L17=0,,L16/L17) -> 0.12095999 | W16: =IF(M17=0,,M16/M17) -> 0.12936016 | X16: =IF(N17=0,,N16/N17) -> 0.13879271
D17: Invested Capital | F17: =Historicals!C146 -> 2945580.1 | G17: =Historicals!D146 -> 3018440.8 | H17: =Historicals!E146 -> 3130109.7 | I17: =Historicals!F146 -> 3214235.4 | J17: =Historicals!G146 -> 3255575.9 | K17: =Historicals!H146 -> 3229993 | L17: =Historicals!I146 -> 3559273.5 | M17: =Historicals!J146 -> 3725927.5 | N17: =Historicals!K146 -> 3954011.7
B19: Gross Margin | C19: = | D19: Gross Profit | E19: = | F19: =Historicals!C6 -> 314505 | G19: =Historicals!D6 -> 358125 | H19: =Historicals!E6 -> 439345 | I19: =Historicals!F6 -> 512379 | J19: =Historicals!G6 -> 493395 | K19: =Historicals!H6 -> 547369 | L19: =Historicals!I6 -> 588543 | M19: =Historicals!J6 -> 651987 | N19: =Historicals!K6 -> 751295 | O19: = | P19: =IF(F20=0,,F19/F20) -> 0.53068115 | Q19: =IF(G20=0,,G19/G20) -> 0.5317293 | R19: =IF(H20=0,,H19/H20) -> 0.5783199 | S19: =IF(I20=0,,I19/I20) -> 0.58998504 | T19: =IF(J20=0,,J19/J20) -> 0.58789711 | U19: =IF(K20=0,,K19/K20) -> 0.58617872 | V19: =IF(L20=0,,L19/L20) -> 0.59453712 | W19: =IF(M20=0,,M19/M20) -> 0.6232609 | X19: =IF(N20=0,,N19/N20) -> 0.66245747
D20: =+D29 -> Revenue | F20: =Historicals!C4 -> 592644 | G20: =Historicals!D4 -> 673510 | H20: =Historicals!E4 -> 759692 | I20: =Historicals!F4 -> 868461 | J20: =Historicals!G4 -> 839254 | K20: =Historicals!H4 -> 933792 | L20: =Historicals!I4 -> 989918 | M20: =Historicals!J4 -> 1046090 | N20: =Historicals!K4 -> 1134103
B22: R&D% of Revenue | C22: = | D22: R&D | E22: = | F22: =Historicals!C9*-1 -> 46109 | G22: =Historicals!D9*-1 -> 48058 | H22: =Historicals!E9*-1 -> 52783 | I22: =Historicals!F9*-1 -> 57232 | J22: =Historicals!G9*-1 -> 56547 | K22: =Historicals!H9*-1 -> 61280 | L22: =Historicals!I9*-1 -> 63743 | M22: =Historicals!J9*-1 -> 64857 | N22: =Historicals!K9*-1 -> 67757 | O22: = | P22: =IF(F23=0,,F22/F23) -> 0.077802188 | Q22: =IF(G23=0,,G22/G23) -> 0.071354546 | R22: =IF(H23=0,,H22/H23) -> 0.069479473 | S22: =IF(I23=0,,I22/I23) -> 0.065900484 | T22: =IF(J23=0,,J22/J23) -> 0.067377695 | U22: =IF(K23=0,,K22/K23) -> 0.065624893 | V22: =IF(L23=0,,L22/L23) -> 0.064392202 | W22: =IF(M23=0,,M22/M23) -> 0.061999446 | X22: =IF(N23=0,,N22/N23) -> 0.059745014
D23: =+D20 -> Revenue | F23: =F20 -> 592644 | G23: =G20 -> 673510 | H23: =H20 -> 759692 | I23: =I20 -> 868461 | J23: =J20 -> 839254 | K23: =K20 -> 933792 | L23: =L20 -> 989918 | M23: =M20 -> 1046090 | N23: =N20 -> 1134103
B25: Cash to Revenue | C25: = | D25: Cash | E25: = | F25: =Historicals!C150*-1 -> 1698196 | G25: =Historicals!D150*-1 -> 1799127 | H25: =Historicals!E150*-1 -> 1886781 | I25: =Historicals!F150*-1 -> 2127627 | J25: =Historicals!G150*-1 -> 2394804 | K25: =Historicals!H150*-1 -> 2364524 | L25: =Historicals!I150*-1 -> 2470759 | M25: =Historicals!J150*-1 -> 2767856 | N25: =Historicals!K150*-1 -> 3035637 | O25: = | P25: =IF(F26=0,,F25/F26) -> 2.8654572 | Q25: =IF(G26=0,,G25/G26) -> 2.6712699 | R25: =IF(H26=0,,H25/H26) -> 2.4836131 | S25: =IF(I26=0,,I25/I26) -> 2.449882 | T25: =IF(J26=0,,J25/J26) -> 2.8534913 | U25: =IF(K26=0,,K25/K26) -> 2.5321742 | V25: =IF(L26=0,,L25/L26) -> 2.4959229 | W25: =IF(M26=0,,M25/M26) -> 2.6459062 | X25: =IF(N26=0,,N25/N26) -> 2.6766855
D26: =+D23 -> Revenue | F26: =F23 -> 592644 | G26: =G23 -> 673510 | H26: =H23 -> 759692 | I26: =I23 -> 868461 | J26: =J23 -> 839254 | K26: =K23 -> 933792 | L26: =L23 -> 989918 | M26: =M23 -> 1046090 | N26: =N23 -> 1134103
B28: FCF Margin | C28: = | D28: FCF | E28: = | F28: =Historicals!C162 -> 172740 | G28: =Historicals!D162 -> 191953 | H28: =Historicals!E162 -> 328376 | I28: =Historicals!F162 -> 156305 | J28: =Historicals!G162 -> 158786 | K28: =Historicals!H162 -> 314173 | L28: =Historicals!I162 -> 425043 | M28: =Historicals!J162 -> 309238 | N28: =Historicals!K162 -> 509742 | O28: = | P28: =IF(F29=0,,F28/F29) -> 0.29147346 | Q28: =IF(G29=0,,G28/G29) -> 0.28500393 | R28: =IF(H29=0,,H28/H29) -> 0.43224886 | S28: =IF(I29=0,,I28/I29) -> 0.1799793 | T28: =IF(J29=0,,J28/J29) -> 0.18919898 | U28: =IF(K29=0,,K28/K29) -> 0.33644859 | V28: =IF(L29=0,,L28/L29) -> 0.42937193 | W28: =IF(M29=0,,M28/M29) -> 0.29561319 | X28: =IF(N29=0,,N28/N29) -> 0.44946711
D29: =+D35 -> Revenue | F29: =F26 -> 592644 | G29: =G26 -> 673510 | H29: =H26 -> 759692 | I29: =I26 -> 868461 | J29: =J26 -> 839254 | K29: =K26 -> 933792 | L29: =L26 -> 989918 | M29: =M26 -> 1046090 | N29: =N26 -> 1134103
B31: Depreciation % of Revenue | C31: = | D31: Depreciation | E31: = | F31: =Historicals!C41 -> 159023 | G31: =Historicals!D41 -> 165166 | H31: =Historicals!E41 -> 168229 | I31: =Historicals!F41 -> 170378 | J31: =Historicals!G41 -> 175139 | K31: =Historicals!H41 -> 188058 | L31: =Historicals!I41 -> 162787 | M31: =Historicals!J41 -> 162112 | N31: =Historicals!K41 -> 165450 | O31: = | P31: =IF(F32=0,,F31/F32) -> 0.26832804 | Q31: =IF(G32=0,,G31/G32) -> 0.2452317 | R31: =IF(H32=0,,H31/H32) -> 0.22144369 | S31: =IF(I32=0,,I31/I32) -> 0.19618382 | T31: =IF(J32=0,,J31/J32) -> 0.20868414 | U31: =IF(K32=0,,K31/K32) -> 0.20139174 | V31: =IF(L32=0,,L31/L32) -> 0.16444493 | W31: =IF(M32=0,,M31/M32) -> 0.15496946 | X31: =IF(N32=0,,N31/N32) -> 0.14588622
D32: =+D20 -> Revenue | F32: =F29 -> 592644 | G32: =G29 -> 673510 | H32: =H29 -> 759692 | I32: =I29 -> 868461 | J32: =J29 -> 839254 | K32: =K29 -> 933792 | L32: =L29 -> 989918 | M32: =M29 -> 1046090 | N32: =N29 -> 1134103
B34: Operating Margin | C34: = | D34: EBIT | E34: = | F34: =Historicals!C15 -> 249018 | G34: =Historicals!D15 -> 286556 | H34: =Historicals!E15 -> 360766 | I34: =Historicals!F15 -> 425713 | J34: =Historicals!G15 -> 407081 | K34: =Historicals!H15 -> 463423 | L34: =Historicals!I15 -> 500685 | M34: =Historicals!J15 -> 564903 | N34: =Historicals!K15 -> 658966 | O34: = | P34: =IF(F35=0,,F34/F35) -> 0.42018142 | Q34: =IF(G35=0,,G34/G35) -> 0.42546659 | R34: =IF(H35=0,,H34/H35) -> 0.47488456 | S34: =IF(I35=0,,I34/I35) -> 0.49019242 | T34: =IF(J35=0,,J34/J35) -> 0.48505101 | U34: =IF(K35=0,,K34/K35) -> 0.49628076 | V34: =IF(L35=0,,L34/L35) -> 0.50578432 | W34: =IF(M35=0,,M34/M35) -> 0.54001377 | X34: =IF(N35=0,,N34/N35) -> 0.58104599
D35: =+D41 -> Revenue | F35: =F32 -> 592644 | G35: =G32 -> 673510 | H35: =H32 -> 759692 | I35: =I32 -> 868461 | J35: =J32 -> 839254 | K35: =K32 -> 933792 | L35: =L32 -> 989918 | M35: =M32 -> 1046090 | N35: =N32 -> 1134103
B37: Net Cash % of Revenue | C37: = | D37: Net Cash | E37: = | F37: ='Key Ratios & Metrics'!F79-'Key Ratios & Metrics'!F119 -> 720135.87 | G37: ='Key Ratios & Metrics'!G79-'Key Ratios & Metrics'!G119 -> 801707.23 | H37: ='Key Ratios & Metrics'!H79-'Key Ratios & Metrics'!H119 -> 891812.32 | I37: ='Key Ratios & Metrics'!I79-'Key Ratios & Metrics'!I119 -> 1109340.6 | J37: ='Key Ratios & Metrics'!J79-'Key Ratios & Metrics'!J119 -> 1346048.1 | K37: ='Key Ratios & Metrics'!K79-'Key Ratios & Metrics'!K119 -> 1386639 | L37: ='Key Ratios & Metrics'!L79-'Key Ratios & Metrics'!L119 -> 1476304.5 | M37: ='Key Ratios & Metrics'!M79-'Key Ratios & Metrics'!M119 -> 1734867.5 | N37: ='Key Ratios & Metrics'!N79-'Key Ratios & Metrics'!N119 -> 1978377.3 | O37: = | P37: =IF(F38=0,,F37/F38) -> 1.2151239 | Q37: =IF(G38=0,,G37/G38) -> 1.190342 | R37: =IF(H38=0,,H37/H38) -> 1.173913 | S37: =IF(I38=0,,I37/I38) -> 1.2773638 | T37: =IF(J38=0,,J37/J38) -> 1.6038626 | U37: =IF(K38=0,,K37/K38) -> 1.4849549 | V37: =IF(L38=0,,L37/L38) -> 1.4913402 | W37: =IF(M38=0,,M37/M38) -> 1.6584304 | X37: =IF(N38=0,,N37/N38) -> 1.7444424
D38: =+D35 -> Revenue | F38: =F35 -> 592644 | G38: =G35 -> 673510 | H38: =H35 -> 759692 | I38: =I35 -> 868461 | J38: =J35 -> 839254 | K38: =K35 -> 933792 | L38: =L35 -> 989918 | M38: =M35 -> 1046090 | N38: =N35 -> 1134103
B40: EBT Margin | C40: = | D40: Earning Before Tax | E40: = | F40: =Historicals!C23 -> 266543 | G40: =Historicals!D23 -> 306311 | H40: =Historicals!E23 -> 384187 | I40: =Historicals!F23 -> 448798 | J40: =Historicals!G23 -> 430895 | K40: =Historicals!H23 -> 493036 | L40: =Historicals!I23 -> 525369 | M40: =Historicals!J23 -> 592363 | N40: =Historicals!K23 -> 687800 | O40: = | P40: =IF(F41=0,,F40/F41) -> 0.4497523 | Q40: =IF(G41=0,,G40/G41) -> 0.454798 | R40: =IF(H41=0,,H40/H41) -> 0.50571416 | S40: =IF(I41=0,,I40/I41) -> 0.51677393 | T40: =IF(J41=0,,J40/J41) -> 0.51342621 | U40: =IF(K41=0,,K40/K41) -> 0.52799339 | V40: =IF(L41=0,,L40/L41) -> 0.53071972 | W40: =IF(M41=0,,M40/M41) -> 0.5662639 | X40: =IF(N41=0,,N40/N41) -> 0.60647049
D41: =+D47 -> Revenue | F41: =F38 -> 592644 | G41: =G38 -> 673510 | H41: =H38 -> 759692 | I41: =I38 -> 868461 | J41: =J38 -> 839254 | K41: =K38 -> 933792 | L41: =L38 -> 989918 | M41: =M38 -> 1046090 | N41: =N38 -> 1134103
B43: Tax % of Revenue | C43: = | D43: Tax | E43: = | F43: =Historicals!C25*-1 -> 41322 | G43: =Historicals!D25*-1 -> 58649 | H43: =Historicals!E25*-1 -> 59107 | I43: =Historicals!F25*-1 -> 74329 | J43: =Historicals!G25*-1 -> 70162 | K43: =Historicals!H25*-1 -> 95543 | L43: =Historicals!I25*-1 -> 73614 | M43: =Historicals!J25*-1 -> 86947 | N43: =Historicals!K25*-1 -> 114999 | O43: = | P43: =IF(F44=0,,F43/F44) -> 0.069724826 | Q43: =IF(G44=0,,G43/G44) -> 0.087079628 | R43: =IF(H44=0,,H43/H44) -> 0.077803899 | S43: =IF(I44=0,,I43/I44) -> 0.085587033 | T43: =IF(J44=0,,J43/J44) -> 0.083600436 | U43: =IF(K44=0,,K43/K44) -> 0.10231722 | V43: =IF(L44=0,,L43/L44) -> 0.074363735 | W43: =IF(M44=0,,M43/M44) -> 0.083116175 | X43: =IF(N44=0,,N43/N44) -> 0.10140084
D44: =+D20 -> Revenue | F44: =F41 -> 592644 | G44: =G41 -> 673510 | H44: =H41 -> 759692 | I44: =I41 -> 868461 | J44: =J41 -> 839254 | K44: =K41 -> 933792 | L44: =L41 -> 989918 | M44: =M41 -> 1046090 | N44: =N41 -> 1134103
B46: Net Profit Margin | C46: = | D46: =D10 -> Net Income | E46: = | F46: =Historicals!C27 -> 225221 | G46: =Historicals!D27 -> 247662 | H46: =Historicals!E27 -> 325080 | I46: =Historicals!F27 -> 374469 | J46: =Historicals!G27 -> 360733 | K46: =Historicals!H27 -> 397493 | L46: =Historicals!I27 -> 451755 | M46: =Historicals!J27 -> 505416 | N46: =Historicals!K27 -> 572480 | O46: = | P46: =IF(F47=0,,F46/F47) -> 0.38002747 | Q46: =IF(G47=0,,G46/G47) -> 0.36771837 | R46: =IF(H47=0,,H46/H47) -> 0.42791026 | S46: =IF(I47=0,,I46/I47) -> 0.43118689 | T46: =IF(J47=0,,J46/J47) -> 0.42982577 | U46: =IF(K47=0,,K46/K47) -> 0.42567617 | V46: =IF(L47=0,,L46/L47) -> 0.45635598 | W46: =IF(M47=0,,M46/M47) -> 0.48314772 | X46: =IF(N47=0,,N46/N47) -> 0.5047866
D47: Revenue | F47: =F44 -> 592644 | G47: =G44 -> 673510 | H47: =H44 -> 759692 | I47: =I44 -> 868461 | J47: =J44 -> 839254 | K47: =K44 -> 933792 | L47: =L44 -> 989918 | M47: =M44 -> 1046090 | N47: =N44 -> 1134103
B49: Effective Tax Rate | C49: = | D49: Tax | E49: = | F49: =F43 -> 41322 | G49: =G43 -> 58649 | H49: =H43 -> 59107 | I49: =I43 -> 74329 | J49: =J43 -> 70162 | K49: =K43 -> 95543 | L49: =L43 -> 73614 | M49: =M43 -> 86947 | N49: =N43 -> 114999 | O49: = | P49: =IF(F50=0,,F49/F50) -> 0.15502939 | Q49: =IF(G50=0,,G49/G50) -> 0.1914688 | R49: =IF(H50=0,,H49/H50) -> 0.15384956 | S49: =IF(I50=0,,I49/I50) -> 0.16561794 | T49: =IF(J50=0,,J49/J50) -> 0.16282853 | U49: =IF(K50=0,,K49/K50) -> 0.19378504 | V49: =IF(L50=0,,L49/L50) -> 0.14011866 | W49: =IF(M50=0,,M49/M50) -> 0.14677993 | X49: =IF(N50=0,,N49/N50) -> 0.16719831
D50: =+D40 -> Earning Before Tax | F50: =F40 -> 266543 | G50: =G40 -> 306311 | H50: =H40 -> 384187 | I50: =I40 -> 448798 | J50: =J40 -> 430895 | K50: =K40 -> 493036 | L50: =L40 -> 525369 | M50: =M40 -> 592363 | N50: =N40 -> 687800
B52: Tax Burden | C52: = | D52: Net Income | E52: = | F52: =F46 -> 225221 | G52: =G46 -> 247662 | H52: =H46 -> 325080 | I52: =I46 -> 374469 | J52: =J46 -> 360733 | K52: =K46 -> 397493 | L52: =L46 -> 451755 | M52: =M46 -> 505416 | N52: =N46 -> 572480 | O52: = | P52: =IF(F53=0,,F52/F53) -> 0.84497061 | Q52: =IF(G53=0,,G52/G53) -> 0.8085312 | R52: =IF(H53=0,,H52/H53) -> 0.84615044 | S52: =IF(I53=0,,I52/I53) -> 0.83438206 | T52: =IF(J53=0,,J52/J53) -> 0.83717147 | U52: =IF(K53=0,,K52/K53) -> 0.80621496 | V52: =IF(L53=0,,L52/L53) -> 0.85988134 | W52: =IF(M53=0,,M52/M53) -> 0.85322007 | X52: =IF(N53=0,,N52/N53) -> 0.83233498
D53: =+D50 -> Earning Before Tax | F53: =F50 -> 266543 | G53: =G50 -> 306311 | H53: =H50 -> 384187 | I53: =I50 -> 448798 | J53: =J50 -> 430895 | K53: =K50 -> 493036 | L53: =L50 -> 525369 | M53: =M50 -> 592363 | N53: =N50 -> 687800
B55: Net Interest Income % EBIT | C55: = | D55: Net Interest Income | E55: = | F55: =Historicals!C19 -> 16661 | G55: =Historicals!D19 -> 18341 | H55: =Historicals!E19 -> 19966 | I55: =Historicals!F19 -> 21750 | J55: =Historicals!G19 -> 22182 | K55: =Historicals!H19 -> 21501 | L55: =Historicals!I19 -> 23222 | M55: =Historicals!J19 -> 26463 | N55: =Historicals!K19 -> 26146 | O55: = | P55: =IF(F56=0,,F55/F56) -> 0.06690681 | Q55: =IF(G56=0,,G55/G56) -> 0.064004941 | R55: =IF(H56=0,,H55/H56) -> 0.055343353 | S55: =IF(I56=0,,I55/I56) -> 0.051090758 | T55: =IF(J56=0,,J55/J56) -> 0.054490384 | U55: =IF(K56=0,,K55/K56) -> 0.046396057 | V55: =IF(L56=0,,L55/L56) -> 0.046380459 | W55: =IF(M56=0,,M55/M56) -> 0.046845211 | X55: =IF(N56=0,,N55/N56) -> 0.039677313
D56: EBIT | F56: =F34 -> 249018 | G56: =G34 -> 286556 | H56: =H34 -> 360766 | I56: =I34 -> 425713 | J56: =J34 -> 407081 | K56: =K34 -> 463423 | L56: =L34 -> 500685 | M56: =M34 -> 564903 | N56: =N34 -> 658966
B58: CapEx % of Revenue | C58: = | D58: CapEx | E58: = | F58: =Historicals!C51*-1 -> 181305 | G58: =Historicals!D51*-1 -> 205674 | H58: =Historicals!E51*-1 -> 207079 | I58: =Historicals!F51*-1 -> 361949 | J58: =Historicals!G51*-1 -> 330827 | K58: =Historicals!H51*-1 -> 297226 | L58: =Historicals!I51*-1 -> 287452 | M58: =Historicals!J51*-1 -> 356906 | N58: =Historicals!K51*-1 -> 350763 | O58: = | P58: =IF(F59=0,,F58/F59) -> 0.30592565 | Q58: =IF(G59=0,,G58/G59) -> 0.30537631 | R58: =IF(H59=0,,H58/H59) -> 0.27258284 | S58: =IF(I59=0,,I58/I59) -> 0.41677059 | T58: =IF(J59=0,,J58/J59) -> 0.39419175 | U58: =IF(K59=0,,K58/K59) -> 0.31830001 | V58: =IF(L59=0,,L58/L59) -> 0.29037961 | W58: =IF(M59=0,,M58/M59) -> 0.34118097 | X58: =IF(N59=0,,N58/N59) -> 0.30928672
D59: Revenue | F59: =F44 -> 592644 | G59: =G44 -> 673510 | H59: =H44 -> 759692 | I59: =I44 -> 868461 | J59: =J44 -> 839254 | K59: =K44 -> 933792 | L59: =L44 -> 989918 | M59: =M44 -> 1046090 | N59: =N44 -> 1134103
B61: FCF Conversion | C61: = | D61: FCF | E61: = | F61: =F28 -> 172740 | G61: =G28 -> 191953 | H61: =H28 -> 328376 | I61: =I28 -> 156305 | J61: =J28 -> 158786 | K61: =K28 -> 314173 | L61: =L28 -> 425043 | M61: =M28 -> 309238 | N61: =N28 -> 509742 | O61: = | P61: =IF(F62=0,,F61/F62) -> 0.76697999 | Q61: =IF(G62=0,,G61/G62) -> 0.77506036 | R61: =IF(H62=0,,H61/H62) -> 1.010139 | S61: =IF(I62=0,,I61/I62) -> 0.41740438 | T61: =IF(J62=0,,J61/J62) -> 0.44017598 | U61: =IF(K62=0,,K61/K62) -> 0.79038625 | V61: =IF(L62=0,,L61/L62) -> 0.9408706 | W61: =IF(M62=0,,M61/M62) -> 0.61184846 | X61: =IF(N62=0,,N61/N62) -> 0.89041015
D62: Net Income | F62: =F46 -> 225221 | G62: =G46 -> 247662 | H62: =H46 -> 325080 | I62: =I46 -> 374469 | J62: =J46 -> 360733 | K62: =K46 -> 397493 | L62: =L46 -> 451755 | M62: =M46 -> 505416 | N62: =N46 -> 572480
B65: Asset Utilization Ratios
B66: all figures in millions of New Taiwan Dollors NTD
F67: =F4 -> 45352 | G67: =G4 -> 45473 | H67: =H4 -> 45565 | I67: =I4 -> 45657 | J67: =J4 -> 45747 | K67: =K4 -> 45838 | L67: =L4 -> 45930 | M67: =M4 -> 46022 | N67: =N4 -> 46112 | P67: =+F67 -> 45352 | Q67: =+G67 -> 45473 | R67: =+H67 -> 45565 | S67: =+I67 -> 45657 | T67: =+J67 -> 45747 | U67: =+K67 -> 45838 | V67: =+L67 -> 45930 | W67: =+M67 -> 46022 | X67: =+N67 -> 46112
B69: CapEx Coverage Ratio | C69: = | D69: Operating Cash Flow | E69: = | F69: =Historicals!C45 -> 436311 | G69: =Historicals!D45 -> 377668 | H69: =Historicals!E45 -> 391993 | I69: =Historicals!F45 -> 620205 | J69: =Historicals!G45 -> 625574 | K69: =Historicals!H45 -> 497064 | L69: =Historicals!I45 -> 426829 | M69: =Historicals!J45 -> 725509 | N69: =Historicals!K45 -> 689976 | O69: = | P69: =IF(F70=0,,F69/F70) -> 2.4065029 | Q69: =IF(G70=0,,G69/G70) -> 1.8362457 | R69: =IF(H70=0,,H69/H70) -> 1.8929636 | S69: =IF(I70=0,,I69/I70) -> 1.7135149 | T69: =IF(J70=0,,J69/J70) -> 1.89094 | U69: =IF(K70=0,,K69/K70) -> 1.6723436 | V69: =IF(L70=0,,L69/L70) -> 1.4848705 | W69: =IF(M70=0,,M69/M70) -> 2.0327733 | X69: =IF(N70=0,,N69/N70) -> 1.9670718
D70: CapEx | F70: =Historicals!C51*-1 -> 181305 | G70: =Historicals!D51*-1 -> 205674 | H70: =Historicals!E51*-1 -> 207079 | I70: =Historicals!F51*-1 -> 361949 | J70: =Historicals!G51*-1 -> 330827 | K70: =Historicals!H51*-1 -> 297226 | L70: =Historicals!I51*-1 -> 287452 | M70: =Historicals!J51*-1 -> 356906 | N70: =Historicals!K51*-1 -> 350763
B72: Asset Turnover | C72: = | D72: =+D20 -> Revenue | E72: = | F72: =F47 -> 592644 | G72: =G47 -> 673510 | H72: =H47 -> 759692 | I72: =I47 -> 868461 | J72: =J47 -> 839254 | K72: =K47 -> 933792 | L72: =L47 -> 989918 | M72: =M47 -> 1046090 | N72: =N47 -> 1134103 | O72: = | P72: =IF(F73=0,,F72/F73) -> 0.10239377 | Q72: =IF(G73=0,,G72/G73) -> 0.11258258 | R72: =IF(H73=0,,H72/H73) -> 0.12321345 | S72: =IF(I73=0,,I72/I73) -> 0.1297772 | T72: =IF(J73=0,,J72/J73) -> 0.11765319 | U72: =IF(K73=0,,K72/K73) -> 0.13327795 | V72: =IF(L73=0,,L72/L73) -> 0.13460751 | W72: =IF(M73=0,,M72/M73) -> 0.13186523 | X72: =IF(N73=0,,N72/N73) -> 0.13094441
D73: =+D11 -> Total Assets | F73: =Historicals!C96 -> 5787891 | G73: =Historicals!D96 -> 5982364 | H73: =Historicals!E96 -> 6165658 | I73: =Historicals!F96 -> 6691938 | J73: =Historicals!G96 -> 7133287 | K73: =Historicals!H96 -> 7006350 | L73: =Historicals!I96 -> 7354107 | M73: =Historicals!J96 -> 7933024 | N73: =Historicals!K96 -> 8660950
B75: PPE Turnover | C75: = | D75: =+D72 -> Revenue | E75: = | F75: =F72 -> 592644 | G75: =G72 -> 673510 | H75: =H72 -> 759692 | I75: =I72 -> 868461 | J75: =J72 -> 839254 | K75: =K72 -> 933792 | L75: =L72 -> 989918 | M75: =M72 -> 1046090 | N75: =N72 -> 1134103 | O75: = | P75: =IF(F76=0,,F75/F76) -> 0.19419185 | Q75: =IF(G76=0,,G75/G76) -> 0.21685137 | R75: =IF(H76=0,,H75/H76) -> 0.24732786 | S75: =IF(I76=0,,I75/I76) -> 0.26845946 | T75: =IF(J76=0,,J75/J76) -> 0.24678091 | U75: =IF(K76=0,,K75/K76) -> 0.27576349 | V75: =IF(L76=0,,L75/L76) -> 0.28288698 | W75: =IF(M76=0,,M75/M76) -> 0.28335186 | X75: =IF(N76=0,,N75/N76) -> 0.28677498
D76: PPE | F76: =Historicals!C92 -> 3051848 | G76: =Historicals!D92 -> 3105860 | H76: =Historicals!E92 -> 3071599 | I76: =Historicals!F92 -> 3234980 | J76: =Historicals!G92 -> 3400806 | K76: =Historicals!H92 -> 3386206 | L76: =Historicals!I92 -> 3499341 | M76: =Historicals!J92 -> 3691841 | N76: =Historicals!K92 -> 3954679
B78: Cash Turnover | C78: = | D78: =D75 -> Revenue | E78: = | F78: =F75 -> 592644 | G78: =G75 -> 673510 | H78: =H75 -> 759692 | I78: =I75 -> 868461 | J78: =J75 -> 839254 | K78: =K75 -> 933792 | L78: =L75 -> 989918 | M78: =M75 -> 1046090 | N78: =N75 -> 1134103 | O78: = | P78: =IF(F79=0,,F78/F79) -> 0.34898445 | Q78: =IF(G79=0,,G78/G79) -> 0.37435378 | R78: =IF(H79=0,,H78/H79) -> 0.4026392 | S78: =IF(I79=0,,I78/I79) -> 0.40818292 | T78: =IF(J79=0,,J78/J79) -> 0.35044789 | U78: =IF(K79=0,,K78/K79) -> 0.39491754 | V78: =IF(L79=0,,L78/L79) -> 0.4006534 | W78: =IF(M79=0,,M78/M79) -> 0.37794235 | X78: =IF(N79=0,,N78/N79) -> 0.37359638
D79: Cash | F79: =Historicals!C83 -> 1698196 | G79: =Historicals!D83 -> 1799127 | H79: =Historicals!E83 -> 1886781 | I79: =Historicals!F83 -> 2127627 | J79: =Historicals!G83 -> 2394804 | K79: =Historicals!H83 -> 2364524 | L79: =Historicals!I83 -> 2470759 | M79: =Historicals!J83 -> 2767856 | N79: =Historicals!K83 -> 3035637
B81: Cash Days | C81: = | D81: Cash x 365 | E81: = | F81: =Historicals!C83*365 -> 619841540 | G81: =Historicals!D83*365 -> 656681355 | H81: =Historicals!E83*365 -> 688675065 | I81: =Historicals!F83*365 -> 776583855 | J81: =Historicals!G83*365 -> 874103460 | K81: =Historicals!H83*365 -> 863051260 | L81: =Historicals!I83*365 -> 901827035 | M81: =Historicals!J83*365 -> 1010267440 | N81: =Historicals!K83*365 -> 1108007505 | O81: = | P81: =IF(F82=0,,F81/F82) -> 1045.8919 | Q81: =IF(G82=0,,G81/G82) -> 975.01352 | R81: =IF(H82=0,,H81/H82) -> 906.51878 | S81: =IF(I82=0,,I81/I82) -> 894.20694 | T81: =IF(J82=0,,J81/J82) -> 1041.5243 | U81: =IF(K82=0,,K81/K82) -> 924.24358 | V81: =IF(L82=0,,L81/L82) -> 911.01186 | W81: =IF(M82=0,,M81/M82) -> 965.75576 | X81: =IF(N82=0,,N81/N82) -> 976.99019
D82: =+D78 -> Revenue | F82: =F78 -> 592644 | G82: =G78 -> 673510 | H82: =H78 -> 759692 | I82: =I78 -> 868461 | J82: =J78 -> 839254 | K82: =K78 -> 933792 | L82: =L78 -> 989918 | M82: =M78 -> 1046090 | N82: =N78 -> 1134103
B84: A/R Turnover | C84: = | D84: =D78 -> Revenue | E84: = | F84: =F82 -> 592644 | G84: =G82 -> 673510 | H84: =H82 -> 759692 | I84: =I82 -> 868461 | J84: =J82 -> 839254 | K84: =K82 -> 933792 | L84: =L82 -> 989918 | M84: =M82 -> 1046090 | N84: =N82 -> 1134103 | O84: = | P84: =IF(F85=0,,F84/F85) -> 2.9341717 | Q84: =IF(G85=0,,G84/G85) -> 3.2039865 | R84: =IF(H85=0,,H84/H85) -> 3.0390841 | S84: =IF(I85=0,,I84/I85) -> 3.1918387 | T84: =IF(J85=0,,J84/J85) -> 3.4402846 | U84: =IF(K85=0,,K84/K85) -> 3.9620341 | V84: =IF(L85=0,,L84/L85) -> 3.2159616 | W84: =IF(M85=0,,M84/M85) -> 3.7122903 | X84: =IF(N85=0,,N84/N85) -> 3.1242077
D85: Accounts Receivable | F85: =Historicals!C85 -> 201980 | G85: =Historicals!D85 -> 210210 | H85: =Historicals!E85 -> 249974 | I85: =Historicals!F85 -> 272088 | J85: =Historicals!G85 -> 243949 | K85: =Historicals!H85 -> 235685 | L85: =Historicals!I85 -> 307814 | M85: =Historicals!J85 -> 281791 | N85: =Historicals!K85 -> 363005
B87: A/R Days | C87: = | D87: Accounts Receivable x 365 | E87: = | F87: =F85*365 -> 73722700 | G87: =G85*365 -> 76726650 | H87: =H85*365 -> 91240510 | I87: =I85*365 -> 99312120 | J87: =J85*365 -> 89041385 | K87: =K85*365 -> 86025025 | L87: =L85*365 -> 112352110 | M87: =M85*365 -> 102853715 | N87: =N85*365 -> 132496825 | O87: = | P87: =IF(F88=0,,F87/F88) -> 124.39626 | Q87: =IF(G88=0,,G87/G88) -> 113.92058 | R87: =IF(H88=0,,H87/H88) -> 120.10198 | S87: =IF(I88=0,,I87/I88) -> 114.35415 | T87: =IF(J88=0,,J87/J88) -> 106.09587 | U87: =IF(K88=0,,K87/K88) -> 92.124397 | V87: =IF(L88=0,,L87/L88) -> 113.49638 | W87: =IF(M88=0,,M87/M88) -> 98.322052 | X87: =IF(N88=0,,N87/N88) -> 116.82962
D88: =+D84 -> Revenue | F88: =F84 -> 592644 | G88: =G84 -> 673510 | H88: =H84 -> 759692 | I88: =I84 -> 868461 | J88: =J84 -> 839254 | K88: =K84 -> 933792 | L88: =L84 -> 989918 | M88: =M84 -> 1046090 | N88: =N84 -> 1134103
B90: Inventory Turnover | C90: = | D90: =+D96 -> COGS | E90: = | F90: =Historicals!C5*-1 -> 278139 | G90: =Historicals!D5*-1 -> 315385 | H90: =Historicals!E5*-1 -> 320347 | I90: =Historicals!F5*-1 -> 356082 | J90: =Historicals!G5*-1 -> 345859 | K90: =Historicals!H5*-1 -> 386423 | L90: =Historicals!I5*-1 -> 401375 | M90: =Historicals!J5*-1 -> 394103 | N90: =Historicals!K5*-1 -> 382808 | O90: = | P90: =IF(F91=0,,F90/F91) -> 1.0412394 | Q90: =IF(G91=0,,G90/G91) -> 1.1574144 | R90: =IF(H91=0,,H90/H91) -> 1.0937675 | S90: =IF(I91=0,,I90/I91) -> 1.2369585 | T90: =IF(J91=0,,J90/J91) -> 1.1788451 | U90: =IF(K91=0,,K90/K91) -> 1.2703176 | V90: =IF(L91=0,,L90/L91) -> 1.390337 | W90: =IF(M91=0,,M90/M91) -> 1.3678907 | X90: =IF(N91=0,,N90/N91) -> 1.2290996
D91: Inventory | F91: =Historicals!C86 -> 267123 | G91: =Historicals!D86 -> 272491 | H91: =Historicals!E86 -> 292884 | I91: =Historicals!F86 -> 287869 | J91: =Historicals!G86 -> 293388 | K91: =Historicals!H86 -> 304194 | L91: =Historicals!I86 -> 288689 | M91: =Historicals!J86 -> 288110 | N91: =Historicals!K86 -> 311454
B93: Inventory Days | C93: = | D93: Inventory x 365 | E93: = | F93: =F91*365 -> 97499895 | G93: =G91*365 -> 99459215 | H93: =H91*365 -> 106902660 | I93: =I91*365 -> 105072185 | J93: =J91*365 -> 107086620 | K93: =K91*365 -> 111030810 | L93: =L91*365 -> 105371485 | M93: =M91*365 -> 105160150 | N93: =N91*365 -> 113680710 | O93: = | P93: =IF(F94=0,,F93/F94) -> 350.54377 | Q93: =IF(G94=0,,G93/G94) -> 315.3581 | R93: =IF(H94=0,,H93/H94) -> 333.70895 | S93: =IF(I94=0,,I93/I94) -> 295.07862 | T93: =IF(J94=0,,J93/J94) -> 309.62508 | U93: =IF(K94=0,,K93/K94) -> 287.32971 | V93: =IF(L94=0,,L93/L94) -> 262.52628 | W93: =IF(M94=0,,M93/M94) -> 266.83418 | X93: =IF(N94=0,,N93/N94) -> 296.96535
D94: =+D90 -> COGS | F94: =F90 -> 278139 | G94: =G90 -> 315385 | H94: =H90 -> 320347 | I94: =I90 -> 356082 | J94: =J90 -> 345859 | K94: =K90 -> 386423 | L94: =L90 -> 401375 | M94: =M90 -> 394103 | N94: =N90 -> 382808
B96: A/P Turnover | C96: = | D96: COGS | E96: = | F96: =F94 -> 278139 | G96: =G94 -> 315385 | H96: =H94 -> 320347 | I96: =I94 -> 356082 | J96: =J94 -> 345859 | K96: =K94 -> 386423 | L96: =L94 -> 401375 | M96: =M94 -> 394103 | N96: =N94 -> 382808 | O96: = | P96: =IF(F97=0,,F96/F97) -> 4.8279639 | Q96: =IF(G97=0,,G96/G97) -> 4.9319749 | R96: =IF(H97=0,,H96/H97) -> 4.5233973 | S96: =IF(I97=0,,I96/I97) -> 4.7972032 | T96: =IF(J97=0,,J96/J97) -> 4.5002082 | U96: =IF(K97=0,,K96/K97) -> 4.5583801 | V96: =IF(L97=0,,L96/L97) -> 4.6462969 | W96: =IF(M97=0,,M96/M97) -> 4.6733428 | X96: =IF(N97=0,,N96/N97) -> 3.8336004
D97: Accounts Payable | F97: =Historicals!C100 -> 57610 | G97: =Historicals!D100 -> 63947 | H97: =Historicals!E100 -> 70820 | I97: =Historicals!F100 -> 74227 | J97: =Historicals!G100 -> 76854 | K97: =Historicals!H100 -> 84772 | L97: =Historicals!I100 -> 86386 | M97: =Historicals!J100 -> 84330 | N97: =Historicals!K100 -> 99856
B99: A/P Days | C99: = | D99: Accounts Payable x 365 | E99: = | F99: =+F97*365 -> 21027650 | G99: =+G97*365 -> 23340655 | H99: =+H97*365 -> 25849300 | I99: =+I97*365 -> 27092855 | J99: =+J97*365 -> 28051710 | K99: =+K97*365 -> 30941780 | L99: =+L97*365 -> 31530890 | M99: =+M97*365 -> 30780450 | N99: =+N97*365 -> 36447440 | O99: = | P99: =IF(F100=0,,F99/F100) -> 75.601228 | Q99: =IF(G100=0,,G99/G100) -> 74.006865 | R99: =IF(H100=0,,H99/H100) -> 80.691563 | S99: =IF(I100=0,,I99/I100) -> 76.086 | T99: =IF(J100=0,,J99/J100) -> 81.107359 | U99: =IF(K100=0,,K99/K100) -> 80.072304 | V99: =IF(L100=0,,L99/L100) -> 78.557185 | W99: =IF(M100=0,,M99/M100) -> 78.102552 | X99: =IF(N100=0,,N99/N100) -> 95.210758
D100: COGS | F100: =+F96 -> 278139 | G100: =+G96 -> 315385 | H100: =+H96 -> 320347 | I100: =+I96 -> 356082 | J100: =+J96 -> 345859 | K100: =+K96 -> 386423 | L100: =+L96 -> 401375 | M100: =+M96 -> 394103 | N100: =+N96 -> 382808
B102: Cash Conversion Cycle / WC Funding Gap | C102: = | D102: AR Days + Inventory Days - AP Days | E102: = | P102: =+P87+P93-P99 -> 399.33881 | Q102: =+Q87+Q93-Q99 -> 355.27182 | R102: =+R87+R93-R99 -> 373.11936 | S102: =+S87+S93-S99 -> 333.34677 | T102: =+T87+T93-T99 -> 334.61359 | U102: =+U87+U93-U99 -> 299.38181 | V102: =+V87+V93-V99 -> 297.46547 | W102: =+W87+W93-W99 -> 287.05368 | X102: =+X87+X93-X99 -> 318.58421
B105: Leverage Ratios
B106: all figures in millions of New Taiwan Dollors NTD
F107: =F67 -> 45352 | G107: =G67 -> 45473 | H107: =H67 -> 45565 | I107: =I67 -> 45657 | J107: =J67 -> 45747 | K107: =K67 -> 45838 | L107: =L67 -> 45930 | M107: =M67 -> 46022 | N107: =N67 -> 46112 | P107: =+F107 -> 45352 | Q107: =+G107 -> 45473 | R107: =+H107 -> 45565 | S107: =+I107 -> 45657 | T107: =+J107 -> 45747 | U107: =+K107 -> 45838 | V107: =+L107 -> 45930 | W107: =+M107 -> 46022 | X107: =+N107 -> 46112
B110: Total Asset to Equity | C110: = | D110: =+D73 -> Total Assets | E110: = | F110: =F73 -> 5787891 | G110: =G73 -> 5982364 | H110: =H73 -> 6165658 | I110: =I73 -> 6691938 | J110: =J73 -> 7133287 | K110: =K73 -> 7006350 | L110: =L73 -> 7354107 | M110: =M73 -> 7933024 | N110: =N73 -> 8660950 | O110: = | P110: =IF(F111=0,,F110/F111) -> 1.5919465 | Q110: =IF(G111=0,,G110/G111) -> 1.5778761 | R110: =IF(H111=0,,H110/H111) -> 1.5452703 | S110: =IF(I111=0,,I110/I111) -> 1.5604215 | T110: =IF(J111=0,,J110/J111) -> 1.5628908 | U110: =IF(K111=0,,K110/K111) -> 1.5294121 | V110: =IF(L111=0,,L110/L111) -> 1.4713196 | W110: =IF(M111=0,,M110/M111) -> 1.4637667 | X110: =IF(N111=0,,N110/N111) -> 1.4702103
D111: =+D8 -> Equity | F111: =F8 -> 3635732 | G111: =G8 -> 3791403 | H111: =H8 -> 3990019 | I111: =I8 -> 4288545 | J111: =J8 -> 4564162 | K111: =K8 -> 4581074 | L111: =L8 -> 4998307 | M111: =M8 -> 5419596 | N111: =N8 -> 5890960
B113: Total Liabilities to Equity | C113: = | D113: Total Liabilities | E113: = | F113: =Historicals!C112 -> 2122175 | G113: =Historicals!D112 -> 2162216 | H113: =Historicals!E112 -> 2143736 | I113: =Historicals!F112 -> 2368362 | J113: =Historicals!G112 -> 2531663 | K113: =Historicals!H112 -> 2389718 | L113: =Historicals!I112 -> 2318529 | M113: =Historicals!J112 -> 2472229 | N113: =Historicals!K112 -> 2728561 | O113: = | P113: =IF(F114=0,,F113/F114) -> 0.58369951 | Q113: =IF(G114=0,,G113/G114) -> 0.57029443 | R113: =IF(H114=0,,H113/H114) -> 0.53727463 | S113: =IF(I114=0,,I113/I114) -> 0.55225304 | T113: =IF(J114=0,,J113/J114) -> 0.55468298 | U113: =IF(K114=0,,K113/K114) -> 0.52165016 | V113: =IF(L114=0,,L113/L114) -> 0.46386286 | W113: =IF(M114=0,,M113/M114) -> 0.45616481 | X113: =IF(N114=0,,N113/N114) -> 0.46317765
D114: =+D111 -> Equity | F114: =+F111 -> 3635732 | G114: =+G111 -> 3791403 | H114: =+H111 -> 3990019 | I114: =+I111 -> 4288545 | J114: =+J111 -> 4564162 | K114: =+K111 -> 4581074 | L114: =+L111 -> 4998307 | M114: =+M111 -> 5419596 | N114: =+N111 -> 5890960
B116: Debt to Equity | C116: = | D116: Interest Bearing Liabilities Only | E116: = | F116: =Historicals!C142 -> 978060.13 | G116: =Historicals!D142 -> 997419.77 | H116: =Historicals!E142 -> 994968.68 | I116: =Historicals!F142 -> 1018286.4 | J116: =Historicals!G142 -> 1048755.9 | K116: =Historicals!H142 -> 977885 | L116: =Historicals!I142 -> 994454.5 | M116: =Historicals!J142 -> 1032988.5 | N116: =Historicals!K142 -> 1057259.7 | O116: = | P116: =IF(F117=0,,F116/F117) -> 0.26901326 | Q116: =IF(G117=0,,G116/G117) -> 0.26307406 | R116: =IF(H117=0,,H116/H117) -> 0.2493644 | S116: =IF(I117=0,,I116/I117) -> 0.23744333 | T116: =IF(J117=0,,J116/J117) -> 0.22978061 | U116: =IF(K117=0,,K116/K117) -> 0.21346195 | V116: =IF(L117=0,,L116/L117) -> 0.19895827 | W116: =IF(M117=0,,M116/M117) -> 0.19060249 | X116: =IF(N117=0,,N116/N117) -> 0.17947154
D117: =+D114 -> Equity | F117: =+F114 -> 3635732 | G117: =+G114 -> 3791403 | H117: =+H114 -> 3990019 | I117: =+I114 -> 4288545 | J117: =+J114 -> 4564162 | K117: =+K114 -> 4581074 | L117: =+L114 -> 4998307 | M117: =+M114 -> 5419596 | N117: =+N114 -> 5890960
B119: Debt to EBIT | C119: = | D119: Interest Bearing Liabilities Only | E119: = | F119: =+F116 -> 978060.13 | G119: =+G116 -> 997419.77 | H119: =+H116 -> 994968.68 | I119: =+I116 -> 1018286.4 | J119: =+J116 -> 1048755.9 | K119: =+K116 -> 977885 | L119: =+L116 -> 994454.5 | M119: =+M116 -> 1032988.5 | N119: =+N116 -> 1057259.7 | O119: = | P119: =IF(F120=0,,F119/F120) -> 3.9276684 | Q119: =IF(G120=0,,G119/G120) -> 3.480715 | R119: =IF(H120=0,,H119/H120) -> 2.7579336 | S119: =IF(I120=0,,I119/I120) -> 2.3919551 | T119: =IF(J120=0,,J119/J120) -> 2.5762832 | U119: =IF(K120=0,,K119/K120) -> 2.1101348 | V119: =IF(L120=0,,L119/L120) -> 1.9861879 | W119: =IF(M120=0,,M119/M120) -> 1.8286122 | X119: =IF(N120=0,,N119/N120) -> 1.6044222
D120: EBIT | F120: =Historicals!C135 -> 249018 | G120: =Historicals!D135 -> 286556 | H120: =Historicals!E135 -> 360766 | I120: =Historicals!F135 -> 425713 | J120: =Historicals!G135 -> 407081 | K120: =Historicals!H135 -> 463423 | L120: =Historicals!I135 -> 500685 | M120: =Historicals!J135 -> 564903 | N120: =Historicals!K135 -> 658966
B122: Net Cash to EBIT | C122: = | D122: Cash - Interest Bearing Liabilities | E122: = | F122: ='Key Ratios & Metrics'!F79-'Key Ratios & Metrics'!F119 -> 720135.87 | G122: ='Key Ratios & Metrics'!G79-'Key Ratios & Metrics'!G119 -> 801707.23 | H122: ='Key Ratios & Metrics'!H79-'Key Ratios & Metrics'!H119 -> 891812.32 | I122: ='Key Ratios & Metrics'!I79-'Key Ratios & Metrics'!I119 -> 1109340.6 | J122: ='Key Ratios & Metrics'!J79-'Key Ratios & Metrics'!J119 -> 1346048.1 | K122: ='Key Ratios & Metrics'!K79-'Key Ratios & Metrics'!K119 -> 1386639 | L122: ='Key Ratios & Metrics'!L79-'Key Ratios & Metrics'!L119 -> 1476304.5 | M122: ='Key Ratios & Metrics'!M79-'Key Ratios & Metrics'!M119 -> 1734867.5 | N122: ='Key Ratios & Metrics'!N79-'Key Ratios & Metrics'!N119 -> 1978377.3 | O122: = | P122: =IF(F123=0,,F122/F123) -> 2.8919029 | Q122: =IF(G123=0,,G122/G123) -> 2.7977332 | R122: =IF(H123=0,,H122/H123) -> 2.4719966 | S122: =IF(I123=0,,I122/I123) -> 2.6058415 | T122: =IF(J123=0,,J122/J123) -> 3.3065854 | U122: =IF(K123=0,,K122/K123) -> 2.992167 | V122: =IF(L123=0,,L122/L123) -> 2.9485695 | W122: =IF(M123=0,,M122/M123) -> 3.0710892 | X122: =IF(N123=0,,N122/N123) -> 3.0022449
D123: EBIT | F123: =+F120 -> 249018 | G123: =+G120 -> 286556 | H123: =+H120 -> 360766 | I123: =+I120 -> 425713 | J123: =+J120 -> 407081 | K123: =+K120 -> 463423 | L123: =+L120 -> 500685 | M123: =+M120 -> 564903 | N123: =+N120 -> 658966
B126: Liquidity Ratios
B127: all figures in millions of New Taiwan Dollors NTD
F128: =F107 -> 45352 | G128: =G107 -> 45473 | H128: =H107 -> 45565 | I128: =I107 -> 45657 | J128: =J107 -> 45747 | K128: =K107 -> 45838 | L128: =L107 -> 45930 | M128: =M107 -> 46022 | N128: =N107 -> 46112 | P128: =+F128 -> 45352 | Q128: =+G128 -> 45473 | R128: =+H128 -> 45565 | S128: =+I128 -> 45657 | T128: =+J128 -> 45747 | U128: =+K128 -> 45838 | V128: =+L128 -> 45930 | W128: =+M128 -> 46022 | X128: =+N128 -> 46112
B131: Current | C131: = | D131: Current Assets | E131: = | F131: =Historicals!C88 -> 2452767 | G131: =Historicals!D88 -> 2591658 | H131: =Historicals!E88 -> 2773914 | I131: =Historicals!F88 -> 3088352 | J131: =Historicals!G88 -> 3345664 | K131: =Historicals!H88 -> 3264918 | L131: =Historicals!I88 -> 3436015 | M131: =Historicals!J88 -> 3817131 | N131: =Historicals!K88 -> 4265512 | O131: = | P131: =IF(F132=0,,F131/F132) -> 2.3901918 | Q131: =IF(G132=0,,G131/G132) -> 2.4707965 | R131: =IF(H132=0,,H131/H132) -> 2.5674903 | S131: =IF(I132=0,,I131/I132) -> 2.4423021 | T131: =IF(J132=0,,J131/J132) -> 2.3900963 | U131: =IF(K132=0,,K131/K132) -> 2.3704965 | V131: =IF(L132=0,,L131/L132) -> 2.6930001 | W131: =IF(M132=0,,M131/M132) -> 2.6180256 | X131: =IF(N132=0,,N131/N132) -> 2.4882614
D132: Current Liabilities | F132: =Historicals!C105 -> 1026180 | G132: =Historicals!D105 -> 1048916 | H132: =Historicals!E105 -> 1080399 | I132: =Historicals!F105 -> 1264525 | J132: =Historicals!G105 -> 1399803 | K132: =Historicals!H105 -> 1377314 | L132: =Historicals!I105 -> 1275906 | M132: =Historicals!J105 -> 1458019 | N132: =Historicals!K105 -> 1714254
B134: Quick | C134: = | D134: Current Assets - Inventory | E134: = | F134: =F131-F91 -> 2185644 | G134: =G131-G91 -> 2319167 | H134: =H131-H91 -> 2481030 | I134: =I131-I91 -> 2800483 | J134: =J131-J91 -> 3052276 | K134: =K131-K91 -> 2960724 | L134: =L131-L91 -> 3147326 | M134: =M131-M91 -> 3529021 | N134: =N131-N91 -> 3954058 | O134: = | P134: =IF(F135=0,,F134/F135) -> 2.1298836 | Q134: =IF(G135=0,,G134/G135) -> 2.2110131 | R134: =IF(H135=0,,H134/H135) -> 2.2964016 | S134: =IF(I135=0,,I134/I135) -> 2.2146521 | T134: =IF(J135=0,,J134/J135) -> 2.180504 | U134: =IF(K135=0,,K134/K135) -> 2.1496362 | V134: =IF(L135=0,,L134/L135) -> 2.4667381 | W134: =IF(M135=0,,M134/M135) -> 2.4204218 | X134: =IF(N135=0,,N134/N135) -> 2.3065765
D135: =+D132 -> Current Liabilities | F135: =+F132 -> 1026180 | G135: =+G132 -> 1048916 | H135: =+H132 -> 1080399 | I135: =+I132 -> 1264525 | J135: =+J132 -> 1399803 | K135: =+K132 -> 1377314 | L135: =+L132 -> 1275906 | M135: =+M132 -> 1458019 | N135: =+N132 -> 1714254
B138: Growth Trends
B139: all figures in millions of New Taiwan Dollors NTD
F140: =F128 -> 45352 | G140: =G128 -> 45473 | H140: =H128 -> 45565 | I140: =I128 -> 45657 | J140: =J128 -> 45747 | K140: =K128 -> 45838 | L140: =L128 -> 45930 | M140: =M128 -> 46022 | N140: =N128 -> 46112 | P140: =+F140 -> 45352 | Q140: =+G140 -> 45473 | R140: =+H140 -> 45565 | S140: =+I140 -> 45657 | T140: =+J140 -> 45747 | U140: =+K140 -> 45838 | V140: =+L140 -> 45930 | W140: =+M140 -> 46022 | X140: =+N140 -> 46112
B143: Revenue Growth | C143: = | D143: Change in Revenues | E143: = | G143: =Historicals!D4-Historicals!C4 -> 80866 | H143: =Historicals!E4-Historicals!D4 -> 86182 | I143: =Historicals!F4-Historicals!E4 -> 108769 | J143: =Historicals!G4-Historicals!F4 -> -29207 | K143: =Historicals!H4-Historicals!G4 -> 94538 | L143: =Historicals!I4-Historicals!H4 -> 56126 | M143: =Historicals!J4-Historicals!I4 -> 56172 | N143: =Historicals!K4-Historicals!J4 -> 88013 | O143: = | Q143: =IF(G144=0,,G143/G144) -> 0.13644954 | R143: =IF(H144=0,,H143/H144) -> 0.1279595 | S143: =IF(I144=0,,I143/I144) -> 0.14317513 | T143: =IF(J144=0,,J143/J144) -> -0.033630756 | U143: =IF(K144=0,,K143/K144) -> 0.11264528 | V143: =IF(L144=0,,L143/L144) -> 0.060105462 | W143: =IF(M144=0,,M143/M144) -> 0.056744094 | X143: =IF(N144=0,,N143/N144) -> 0.084135208
D144: Prior Year Revenues | G144: =Historicals!C4 -> 592644 | H144: =Historicals!D4 -> 673510 | I144: =Historicals!E4 -> 759692 | J144: =Historicals!F4 -> 868461 | K144: =Historicals!G4 -> 839254 | L144: =Historicals!H4 -> 933792 | M144: =Historicals!I4 -> 989918 | N144: =Historicals!J4 -> 1046090
B146: EBIT Growth | C146: = | D146: Change in EBIT | E146: = | G146: =Historicals!D15-Historicals!C15 -> 37538 | H146: =Historicals!E15-Historicals!D15 -> 74210 | I146: =Historicals!F15-Historicals!E15 -> 64947 | J146: =Historicals!G15-Historicals!F15 -> -18632 | K146: =Historicals!H15-Historicals!G15 -> 56342 | L146: =Historicals!I15-Historicals!H15 -> 37262 | M146: =Historicals!J15-Historicals!I15 -> 64218 | N146: =Historicals!K15-Historicals!J15 -> 94063 | O146: = | Q146: =IF(G147=0,,G146/G147) -> 0.15074412 | R146: =IF(H147=0,,H146/H147) -> 0.25897207 | S146: =IF(I147=0,,I146/I147) -> 0.18002528 | T146: =IF(J147=0,,J146/J147) -> -0.043766575 | U146: =IF(K147=0,,K146/K147) -> 0.13840489 | V146: =IF(L147=0,,L146/L147) -> 0.080406022 | W146: =IF(M147=0,,M146/M147) -> 0.12826028 | X146: =IF(N147=0,,N146/N147) -> 0.16651177
D147: Prior Year EBIT | G147: =Historicals!C15 -> 249018 | H147: =Historicals!D15 -> 286556 | I147: =Historicals!E15 -> 360766 | J147: =Historicals!F15 -> 425713 | K147: =Historicals!G15 -> 407081 | L147: =Historicals!H15 -> 463423 | M147: =Historicals!I15 -> 500685 | N147: =Historicals!J15 -> 564903
B149: Net Income Growth | C149: = | D149: Change in Net Income | E149: = | G149: =Historicals!D27-Historicals!C27 -> 22441 | H149: =Historicals!E27-Historicals!D27 -> 77418 | I149: =Historicals!F27-Historicals!E27 -> 49389 | J149: =Historicals!G27-Historicals!F27 -> -13736 | K149: =Historicals!H27-Historicals!G27 -> 36760 | L149: =Historicals!I27-Historicals!H27 -> 54262 | M149: =Historicals!J27-Historicals!I27 -> 53661 | N149: =Historicals!K27-Historicals!J27 -> 67064 | O149: = | Q149: =IF(G150=0,,G149/G150) -> 0.099639909 | R149: =IF(H150=0,,H149/H150) -> 0.31259539 | S149: =IF(I150=0,,I149/I150) -> 0.15192876 | T149: =IF(J150=0,,J149/J150) -> -0.036681274 | U149: =IF(K150=0,,K149/K150) -> 0.10190362 | V149: =IF(L150=0,,L149/L150) -> 0.13651058 | W149: =IF(M150=0,,M149/M150) -> 0.11878341 | X149: =IF(N150=0,,N149/N150) -> 0.13269069
D150: Prior Year Net Income | G150: =Historicals!C27 -> 225221 | H150: =Historicals!D27 -> 247662 | I150: =Historicals!E27 -> 325080 | J150: =Historicals!F27 -> 374469 | K150: =Historicals!G27 -> 360733 | L150: =Historicals!H27 -> 397493 | M150: =Historicals!I27 -> 451755 | N150: =Historicals!J27 -> 505416
B152: Total Asset Growth | C152: = | D152: Change in Total Assets | E152: = | G152: =Historicals!D96-Historicals!C96 -> 194473 | H152: =Historicals!E96-Historicals!D96 -> 183294 | I152: =Historicals!F96-Historicals!E96 -> 526280 | J152: =Historicals!G96-Historicals!F96 -> 441349 | K152: =Historicals!H96-Historicals!G96 -> -126937 | L152: =Historicals!I96-Historicals!H96 -> 347757 | M152: =Historicals!J96-Historicals!I96 -> 578917 | N152: =Historicals!K96-Historicals!J96 -> 727926 | O152: = | Q152: =IF(G153=0,,G152/G153) -> 0.033599976 | R152: =IF(H153=0,,H152/H153) -> 0.030639058 | S152: =IF(I153=0,,I152/I153) -> 0.085356664 | T152: =IF(J153=0,,J152/J153) -> 0.065952344 | U152: =IF(K153=0,,K152/K153) -> -0.017795022 | V152: =IF(L153=0,,L152/L153) -> 0.049634546 | W152: =IF(M153=0,,M152/M153) -> 0.078720231 | X152: =IF(N153=0,,N152/N153) -> 0.091758956
D153: Prior Year Total Assets | G153: =Historicals!C96 -> 5787891 | H153: =Historicals!D96 -> 5982364 | I153: =Historicals!E96 -> 6165658 | J153: =Historicals!F96 -> 6691938 | K153: =Historicals!G96 -> 7133287 | L153: =Historicals!H96 -> 7006350 | M153: =Historicals!I96 -> 7354107 | N153: =Historicals!J96 -> 7933024
B155: Degree of Operating Leverage | C155: = | D155: Percentage Change in EBIT | E155: = | G155: =+Q146 -> 0.15074412 | H155: =+R146 -> 0.25897207 | I155: =+S146 -> 0.18002528 | J155: =+T146 -> -0.043766575 | K155: =+U146 -> 0.13840489 | L155: =+V146 -> 0.080406022 | M155: =+W146 -> 0.12826028 | N155: =+X146 -> 0.16651177 | O155: = | Q155: =IF(G156=0,,G155/G156) -> 1.104761 | R155: =IF(H156=0,,H155/H156) -> 2.0238597 | S155: =IF(I156=0,,I155/I156) -> 1.2573782 | T155: =IF(J156=0,,J155/J156) -> 1.3013854 | U155: =IF(K156=0,,K155/K156) -> 1.228679 | V155: =IF(L156=0,,L155/L156) -> 1.337749 | W155: =IF(M156=0,,M155/M156) -> 2.2603283 | X155: =IF(N156=0,,N155/N156) -> 1.9790974
D156: Percentage Change in Revenue | G156: =+Q143 -> 0.13644954 | H156: =+R143 -> 0.1279595 | I156: =+S143 -> 0.14317513 | J156: =+T143 -> -0.033630756 | K156: =+U143 -> 0.11264528 | L156: =+V143 -> 0.060105462 | M156: =+W143 -> 0.056744094 | N156: =+X143 -> 0.084135208
...

Sheet Historicals
B1: Income Statement | C1: Actuals
B2: all figures in millions of New Taiwan Dollors NTD | C2: 45352 | D2: =EOMONTH(C2,3) -> 45473 | E2: =EOMONTH(D2,3) -> 45565 | F2: =EOMONTH(E2,3) -> 45657 | G2: =EOMONTH(F2,3) -> 45747 | H2: =EOMONTH(G2,3) -> 45838 | I2: =EOMONTH(H2,3) -> 45930 | J2: =EOMONTH(I2,3) -> 46022 | K2: =EOMONTH(J2,3) -> 46112 | N2: Revenue Schedule by Technology & Platform | Q2: =Model!G2 -> 45382 | R2: =Model!H2 -> 45473 | S2: =Model!I2 -> 45565 | T2: =Model!J2 -> 45656 | U2: =Model!K2 -> 45746 | V2: =Model!L2 -> 45838 | W2: =Model!M2 -> 45930 | X2: =Model!N2 -> 46021 | Y2: =Model!O2 -> 46111
B4: Net Revenue | C4: 592644 | D4: 673510 | E4: 759692 | F4: 868461 | G4: 839254 | H4: 933792 | I4: 989918 | J4: 1046090 | K4: 1134103 | N4: Revenue by Technology
B5: Cost of Revenue | C5: -278139 | D5: -315385 | E5: -320347 | F5: -356082 | G5: -345859 | H5: -386423 | I5: -401375 | J5: -394103 | K5: -382808 | N5: 3nm | Q5: 0.09 | R5: 0.15 | S5: 0.2 | T5: 0.26 | U5: 0.22 | V5: 0.24 | W5: 0.23 | X5: 0.28 | Y5: 0.28
B6: Gross Profit | C6: 314505 | D6: 358125 | E6: 439345 | F6: 512379 | G6: 493395 | H6: 547369 | I6: 588543 | J6: 651987 | K6: 751295 | N6: 5nm | Q6: 0.37 | R6: 0.35 | S6: 0.32 | T6: 0.34 | U6: 0.36 | V6: 0.36 | W6: 0.37 | X6: 0.35 | Y6: 0.35
K7: =K15+K41 -> 824416 | N7: 7nm | Q7: 0.19 | R7: 0.17 | S7: 0.17 | T7: 0.14 | U7: 0.15 | V7: 0.14 | W7: 0.14 | X7: 0.14 | Y7: 0.14
B8: Operating Expenses | N8: 16/17nm | Q8: 0.09 | R8: 0.09 | S8: 0.08 | T8: 0.07 | U8: 0.07 | V8: 0.07 | W8: 0.07 | X8: 0.06 | Y8: 0.07
B9: R&D Expenses | C9: -46109 | D9: -48058 | E9: -52783 | F9: -57232 | G9: -56547 | H9: -61280 | I9: -63743 | J9: -64857 | K9: -67757 | N9: 28nm | Q9: 0.08 | R9: 0.08 | S9: 0.07 | T9: 0.06 | U9: 0.07 | V9: 0.07 | W9: 0.07 | X9: 0.06 | Y9: 0.05
B10: SG&A Expenses | C10: -19248 | D10: -22238 | E10: -26295 | F10: -29108 | G10: -28639 | H10: -23228 | I10: -24022 | J10: -23333 | K10: -26249 | N10: 40/45nm | Q10: 0.05 | R10: 0.05 | S10: 0.04 | T10: 0.03 | U10: 0.03 | V10: 0.03 | W10: 0.03 | X10: 0.03 | Y10: 0.03
B11: Total Operating Expenses | C11: -65357 | D11: -70296 | E11: -79078 | F11: -86340 | G11: -85186 | H11: -84508 | I11: -87765 | J11: -88190 | K11: -94006 | N11: 65nm | Q11: 0.04 | R11: 0.03 | S11: 0.04 | T11: 0.04 | U11: 0.04 | V11: 0.03 | W11: 0.04 | X11: 0.04 | Y11: 0.04
N12: 90nm | Q12: 0.01 | R12: 0.01 | S12: 0.01 | T12: 0.01 | U12: 0.01 | V12: 0.01 | W12: 0.01 | X12: 0.01 | Y12: 0.01
B13: Other operating Income and Expenses | C13: -130 | D13: -1273 | E13: 499 | F13: -326 | G13: -1128 | H13: 562 | I13: -93 | J13: 1106 | K13: 1677 | N13: 0.11/0.13um | Q13: 0.03 | R13: 0.02 | S13: 0.02 | T13: 0.02 | U13: 0.02 | V13: 0.02 | W13: 0.01 | X13: 0.01 | Y13: 0.01
N14: 0.15/0.18um | Q14: 0.04 | R14: 0.04 | S14: 0.04 | T14: 0.03 | U14: 0.03 | V14: 0.03 | W14: 0.03 | X14: 0.02 | Y14: 0.02
B15: Income from Operations | C15: 249018 | D15: 286556 | E15: 360766 | F15: 425713 | G15: 407081 | H15: 463423 | I15: 500685 | J15: 564903 | K15: 658966 | N15: 0.25um and above | Q15: 0.01 | R15: 0.01 | S15: 0.01 | T15: 0 | U15: 0 | V15: 0 | W15: 0 | X15: 0 | Y15: 0
B17: Non operating Income and Expenses | N17: Revenue by Platform
B18: Share of Profits and Associated | C18: 878 | D18: 1152 | E18: 1561 | F18: 1289 | G18: 1368 | H18: 1222 | I18: 1424 | J18: 1483 | K18: 1685 | N18: HPC | Q18: 0.46 | R18: 0.52 | S18: 0.51 | T18: 0.53 | U18: 0.59 | V18: 0.6 | W18: 0.57 | X18: 0.55 | Y18: 0.61
B19: Net interest Income (Expenses) | C19: 16661 | D19: 18341 | E19: 19966 | F19: 21750 | G19: 22182 | H19: 21501 | I19: 23222 | J19: 26463 | K19: 26146 | N19: Smartphone | Q19: 0.38 | R19: 0.33 | S19: 0.34 | T19: 0.35 | U19: 0.28 | V19: 0.27 | W19: 0.3 | X19: 0.32 | Y19: 0.26
B20: Other gains and Losses | C20: -14 | D20: 262 | E20: 1894 | F20: 46 | G20: 264 | H20: 6890 | I20: 38 | J20: -486 | K20: 1003 | N20: IoT | Q20: 0.06 | R20: 0.06 | S20: 0.07 | T20: 0.05 | U20: 0.05 | V20: 0.05 | W20: 0.05 | X20: 0.05 | Y20: 0.06
B21: Total Non Operating Income and Expenses | C21: 17525 | D21: 19755 | E21: 23421 | F21: 23085 | G21: 23814 | H21: 29613 | I21: 24684 | J21: 27460 | K21: 28834 | N21: Automotive | Q21: 0.06 | R21: 0.05 | S21: 0.05 | T21: 0.04 | U21: 0.05 | V21: 0.05 | W21: 0.05 | X21: 0.05 | Y21: 0.04
N22: DCE | Q22: 0.02 | R22: 0.02 | S22: 0.01 | T22: 0.01 | U22: 0.01 | V22: 0.01 | W22: 0.01 | X22: 0.01 | Y22: 0.01
B23: Income before Income Taxes | C23: 266543 | D23: 306311 | E23: 384187 | F23: 448798 | G23: 430895 | H23: 493036 | I23: 525369 | J23: 592363 | K23: 687800 | N23: others | Q23: 0.02 | R23: 0.02 | S23: 0.02 | T23: 0.02 | U23: 0.02 | V23: 0.02 | W23: 0.02 | X23: 0.02 | Y23: 0.02
B25: Income Tax Expenses | C25: -41322 | D25: -58649 | E25: -59107 | F25: -74329 | G25: -70162 | H25: -95543 | I25: -73614 | J25: -86947 | K25: -114999 | N25: Revenue by Platform
N26: HPC | Q26: =Q18*Model!G$4 -> 272616.24 | R26: =R18*Model!H$4 -> 350225.2 | S26: =S18*Model!I$4 -> 387442.92 | T26: =T18*Model!J$4 -> 460284.33 | U26: =U18*Model!K$4 -> 495159.86 | V26: =V18*Model!L$4 -> 560275.2 | W26: =W18*Model!M$4 -> 564253.26 | X26: =X18*Model!N$4 -> 575349.5 | Y26: =Y18*Model!O$4 -> 691802.83
B27: Net Income | C27: 225221 | D27: 247662 | E27: 325080 | F27: 374469 | G27: 360733 | H27: 397493 | I27: 451755 | J27: 505416 | K27: 572480 | N27: Smartphone | Q27: =Q19*Model!G$4 -> 225204.72 | R27: =R19*Model!H$4 -> 222258.3 | S27: =S19*Model!I$4 -> 258295.28 | T27: =T19*Model!J$4 -> 303961.35 | U27: =U19*Model!K$4 -> 234991.12 | V27: =V19*Model!L$4 -> 252123.84 | W27: =W19*Model!M$4 -> 296975.4 | X27: =X19*Model!N$4 -> 334748.8 | Y27: =Y19*Model!O$4 -> 294866.78
N28: IoT | Q28: =Q20*Model!G$4 -> 35558.64 | R28: =R20*Model!H$4 -> 40410.6 | S28: =S20*Model!I$4 -> 53178.44 | T28: =T20*Model!J$4 -> 43423.05 | U28: =U20*Model!K$4 -> 41962.7 | V28: =V20*Model!L$4 -> 46689.6 | W28: =W20*Model!M$4 -> 49495.9 | X28: =X20*Model!N$4 -> 52304.5 | Y28: =Y20*Model!O$4 -> 68046.18
B29: Other Comprehesive Income (Losses) | C29: 41274 | D29: 13464 | E29: -21056 | F29: 37903 | G29: 31897 | H29: -254502 | I29: 95202 | J29: 71076 | K29: 53996 | N29: Automotive | Q29: =Q21*Model!G$4 -> 35558.64 | R29: =R21*Model!H$4 -> 33675.5 | S29: =S21*Model!I$4 -> 37984.6 | T29: =T21*Model!J$4 -> 34738.44 | U29: =U21*Model!K$4 -> 41962.7 | V29: =V21*Model!L$4 -> 46689.6 | W29: =W21*Model!M$4 -> 49495.9 | X29: =X21*Model!N$4 -> 52304.5 | Y29: =Y21*Model!O$4 -> 45364.12
B30: Comprehensive Income | C30: 266495 | D30: 261126 | E30: 304024 | F30: 412372 | G30: 392630 | H30: 142991 | I30: 546957 | J30: 576492 | K30: 626797 | N30: DCE | Q30: =Q22*Model!G$4 -> 11852.88 | R30: =R22*Model!H$4 -> 13470.2 | S30: =S22*Model!I$4 -> 7596.92 | T30: =T22*Model!J$4 -> 8684.61 | U30: =U22*Model!K$4 -> 8392.54 | V30: =V22*Model!L$4 -> 9337.92 | W30: =W22*Model!M$4 -> 9899.18 | X30: =X22*Model!N$4 -> 10460.9 | Y30: =Y22*Model!O$4 -> 11341.03
N31: others | Q31: =Q23*Model!G$4 -> 11852.88 | R31: =R23*Model!H$4 -> 13470.2 | S31: =S23*Model!I$4 -> 15193.84 | T31: =T23*Model!J$4 -> 17369.22 | U31: =U23*Model!K$4 -> 16785.08 | V31: =V23*Model!L$4 -> 18675.84 | W31: =W23*Model!M$4 -> 19798.36 | X31: =X23*Model!N$4 -> 20921.8 | Y31: =Y23*Model!O$4 -> 22682.06
B32: net income (losses) attributable to shareholder of the parent | C32: 225485 | D32: 247845 | E32: 325258 | F32: 374680 | G32: 361564 | H32: 398273 | I32: 452302 | J32: 505744 | K32: 572480 | N32: Total Rev | Q32: =SUM(Q26:Q31) -> 592644 | R32: =SUM(R26:R31) -> 673510 | S32: =SUM(S26:S31) -> 759692 | T32: =SUM(T26:T31) -> 868461 | U32: =SUM(U26:U31) -> 839254 | V32: =SUM(V26:V31) -> 933792 | W32: =SUM(W26:W31) -> 989918 | X32: =SUM(X26:X31) -> 1046090 | Y32: =SUM(Y26:Y31) -> 1134103
B33: NCI | C33: -264 | D33: -183 | E33: -178 | F33: -211 | G33: -831 | H33: -780 | I33: -547 | J33: -328 | K33: 321
C34: 225221 | D34: 247662 | E34: 325080 | F34: 374469 | G34: 360733 | H34: 397493 | I34: 451755 | J34: 505416 | K34: 572801 | N34: Revenue by Technology
N35: 3nm | Q35: =Q5*Model!G$4 -> 53337.96 | R35: =R5*Model!H$4 -> 101026.5 | S35: =S5*Model!I$4 -> 151938.4 | T35: =T5*Model!J$4 -> 225799.86 | U35: =U5*Model!K$4 -> 184635.88 | V35: =V5*Model!L$4 -> 224110.08 | W35: =W5*Model!M$4 -> 227681.14 | X35: =X5*Model!N$4 -> 292905.2 | Y35: =Y5*Model!O$4 -> 317548.84
B36: Cash flow Statement | N36: 5nm | Q36: =Q6*Model!G$4 -> 219278.28 | R36: =R6*Model!H$4 -> 235728.5 | S36: =S6*Model!I$4 -> 243101.44 | T36: =T6*Model!J$4 -> 295276.74 | U36: =U6*Model!K$4 -> 302131.44 | V36: =V6*Model!L$4 -> 336165.12 | W36: =W6*Model!M$4 -> 366269.66 | X36: =X6*Model!N$4 -> 366131.5 | Y36: =Y6*Model!O$4 -> 396936.05
B37: all figures in millions of New Taiwan Dollors NTD | C37: =C2 -> 45352 | D37: =D2 -> 45473 | E37: =E2 -> 45565 | F37: =F2 -> 45657 | G37: =G2 -> 45747 | H37: =H2 -> 45838 | I37: =I2 -> 45930 | J37: =J2 -> 46022 | K37: =K2 -> 46112 | N37: 7nm | Q37: =Q7*Model!G$4 -> 112602.36 | R37: =R7*Model!H$4 -> 114496.7 | S37: =S7*Model!I$4 -> 129147.64 | T37: =T7*Model!J$4 -> 121584.54 | U37: =U7*Model!K$4 -> 125888.1 | V37: =V7*Model!L$4 -> 130730.88 | W37: =W7*Model!M$4 -> 138588.52 | X37: =X7*Model!N$4 -> 146452.6 | Y37: =Y7*Model!O$4 -> 158774.42
N38: 16/17nm | Q38: =Q8*Model!G$4 -> 53337.96 | R38: =R8*Model!H$4 -> 60615.9 | S38: =S8*Model!I$4 -> 60775.36 | T38: =T8*Model!J$4 -> 60792.27 | U38: =U8*Model!K$4 -> 58747.78 | V38: =V8*Model!L$4 -> 65365.44 | W38: =W8*Model!M$4 -> 69294.26 | X38: =X8*Model!N$4 -> 62765.4 | Y38: =Y8*Model!O$4 -> 79387.21
B39: Cash from Operating Activities | N39: 28nm | Q39: =Q9*Model!G$4 -> 47411.52 | R39: =R9*Model!H$4 -> 53880.8 | S39: =S9*Model!I$4 -> 53178.44 | T39: =T9*Model!J$4 -> 52107.66 | U39: =U9*Model!K$4 -> 58747.78 | V39: =V9*Model!L$4 -> 65365.44 | W39: =W9*Model!M$4 -> 69294.26 | X39: =X9*Model!N$4 -> 62765.4 | Y39: =Y9*Model!O$4 -> 56705.15
B40: Income Before Income Tax | C40: 266543 | D40: 306311 | E40: 384187 | F40: 448798 | G40: 430895 | H40: 493036 | I40: 525369 | J40: 592363 | K40: 687800 | N40: 40/45nm | Q40: =Q10*Model!G$4 -> 29632.2 | R40: =R10*Model!H$4 -> 33675.5 | S40: =S10*Model!I$4 -> 30387.68 | T40: =T10*Model!J$4 -> 26053.83 | U40: =U10*Model!K$4 -> 25177.62 | V40: =V10*Model!L$4 -> 28013.76 | W40: =W10*Model!M$4 -> 29697.54 | X40: =X10*Model!N$4 -> 31382.7 | Y40: =Y10*Model!O$4 -> 34023.09
B41: D&A | C41: 159023 | D41: 165166 | E41: 168229 | F41: 170378 | G41: 175139 | H41: 188058 | I41: 162787 | J41: 162112 | K41: 165450 | N41: 65nm | Q41: =Q11*Model!G$4 -> 23705.76 | R41: =R11*Model!H$4 -> 20205.3 | S41: =S11*Model!I$4 -> 30387.68 | T41: =T11*Model!J$4 -> 34738.44 | U41: =U11*Model!K$4 -> 33570.16 | V41: =V11*Model!L$4 -> 28013.76 | W41: =W11*Model!M$4 -> 39596.72 | X41: =X11*Model!N$4 -> 41843.6 | Y41: =Y11*Model!O$4 -> 45364.12
B42: Share of Profits of Associates | C42: -878 | D42: -1152 | E42: -1561 | F42: -1289 | G42: -1368 | H42: -1222 | I42: -1424 | J42: -1483 | K42: -1685 | N42: 90nm | Q42: =Q12*Model!G$4 -> 5926.44 | R42: =R12*Model!H$4 -> 6735.1 | S42: =S12*Model!I$4 -> 7596.92 | T42: =T12*Model!J$4 -> 8684.61 | U42: =U12*Model!K$4 -> 8392.54 | V42: =V12*Model!L$4 -> 9337.92 | W42: =W12*Model!M$4 -> 9899.18 | X42: =X12*Model!N$4 -> 10460.9 | Y42: =Y12*Model!O$4 -> 11341.03
B43: Income Taxes Paid | C43: -1051 | D43: -88103 | E43: -93295 | F43: -1190 | G43: -1537 | H43: -127347 | I43: -137266 | J43: -1407 | K43: -1501 | N43: 0.11/0.13um | Q43: =Q13*Model!G$4 -> 17779.32 | R43: =R13*Model!H$4 -> 13470.2 | S43: =S13*Model!I$4 -> 15193.84 | T43: =T13*Model!J$4 -> 17369.22 | U43: =U13*Model!K$4 -> 16785.08 | V43: =V13*Model!L$4 -> 18675.84 | W43: =W13*Model!M$4 -> 9899.18 | X43: =X13*Model!N$4 -> 10460.9 | Y43: =Y13*Model!O$4 -> 11341.03
B44: changes in working Capital & Others | C44: 12674 | D44: -4554 | E44: -65567 | F44: 3508 | G44: 22445 | H44: -55461 | I44: -122637 | J44: -26076 | K44: -151088 | N44: 0.15/0.18um | Q44: =Q14*Model!G$4 -> 23705.76 | R44: =R14*Model!H$4 -> 26940.4 | S44: =S14*Model!I$4 -> 30387.68 | T44: =T14*Model!J$4 -> 26053.83 | U44: =U14*Model!K$4 -> 25177.62 | V44: =V14*Model!L$4 -> 28013.76 | W44: =W14*Model!M$4 -> 29697.54 | X44: =X14*Model!N$4 -> 20921.8 | Y44: =Y14*Model!O$4 -> 22682.06
B45: Net Cash from Operating Activities | C45: 436311 | D45: 377668 | E45: 391993 | F45: 620205 | G45: 625574 | H45: 497064 | I45: 426829 | J45: 725509 | K45: 689976 | N45: 0.25um and above | Q45: =Q15*Model!G$4 -> 5926.44 | R45: =R15*Model!H$4 -> 6735.1 | S45: =S15*Model!I$4 -> 7596.92 | T45: =T15*Model!J$4 -> 0 | U45: =U15*Model!K$4 -> 0 | V45: =V15*Model!L$4 -> 0 | W45: =W15*Model!M$4 -> 0 | X45: =X15*Model!N$4 -> 0 | Y45: =Y15*Model!O$4 -> 0
N46: Total Rev | Q46: =SUM(Q35:Q45) -> 592644 | R46: =SUM(R35:R45) -> 673510 | S46: =SUM(S35:S45) -> 759692 | T46: =SUM(T35:T45) -> 868461 | U46: =SUM(U35:U45) -> 839254 | V46: =SUM(V35:V45) -> 933792 | W46: =SUM(W35:W45) -> 989918 | X46: =SUM(X35:X45) -> 1046090 | Y46: =SUM(Y35:Y45) -> 1134103
B47: Cash Flow From Investing Activities
B48: Interest Received | C48: 17410 | D48: 19195 | E48: 21356 | F48: 18473 | G48: 24419 | H48: 26025 | I48: 22351 | J48: 26160 | K48: 26746
B49: Cash Dividend Received | C49: 90 | D49: 805 | E49: 2405 | F49: 207 | G49: 95 | H49: 1091 | I49: 2705 | J49: 49 | K49: 1041
B50: Acquisitions of :
B51: PPE | C51: -181305 | D51: -205674 | E51: -207079 | F51: -361949 | G51: -330827 | H51: -297226 | I51: -287452 | J51: -356906 | K51: -350763
B52: Marketable Financial Instruments | C52: -45800 | D52: -63263 | E52: -54209 | F52: -77351 | G52: -70741 | H52: -61989 | I52: -50445 | J52: -72197 | K52: -91621
B53: Proceeds from Disposal or Redemption of:
B54: PPE | C54: 337 | D54: 156 | E54: 146 | F54: 256 | G54: 128 | H54: 117 | I54: 70 | J54: 482 | K54: 1813
B55: Marketable Financial Instruments | C55: 50224 | D55: 44500 | E55: 34426 | F55: 56885 | G55: 53926 | H55: 73744 | I55: 49196 | J55: 41390 | K55: 61305
B56: Others | C56: -763 | D56: 6673 | E56: 7446 | F56: 51560 | G56: 32808 | H56: 29749 | I56: 3823 | J56: -4939 | K56: -5375
B57: Net Cash from Investing Activities | C57: -159807 | D57: -197608 | E57: -195509 | F57: -311919 | G57: -290192 | H57: -228489 | I57: -259752 | J57: -365961 | K57: -356854
B59: Cash Flow from Financing Activities
B60: Increase (Decrease) in Hedging Financial Liabilities - Bank Loans | C60: -26496 | D60: 0 | E60: 0 | F60: 0 | G60: 0 | H60: 430 | I60: 0 | J60: -95 | K60: -182
B61: Proceeds from issuance of Bonds | C61: 22800 | D61: 11500 | E61: 0 | F61: 0 | G61: 19200 | H61: 14100 | I61: 30100 | J61: 23500 | K61: 17200
B62: Repayments of Bonds | C62: 0 | D62: 0 | E62: -5250 | F62: -1750 | G62: -3000 | H62: -10400 | I62: -39160 | J62: -1750 | K62: -4800
B63: Proceeds from Long Term bank Loans | C63: 6378 | D63: 0 | E63: 17064 | F63: 7455 | G63: 5395 | H63: 0 | I63: 2232 | J63: 3031 | K63: 2020
B64: Repayments of Long Term Bank Loans | C64: -513 | D64: -543 | E64: -604 | F64: -636 | G64: -719 | H64: -719 | I64: -720 | J64: -552 | K64: -390
B65: Interest paid | C65: -1779 | D65: -6641 | E65: -4385 | F65: -5946 | G65: -2516 | H65: -7223 | I65: -4040 | J65: -5350 | K65: -2747
B66: Cash Dividends Paid for Common Stock | C66: -77796 | D66: -90762 | E66: -90763 | F66: -103734 | G66: -103722 | H66: -116697 | I66: -116697 | J66: -129663 | K66: -129663
B67: Repurchases of Tresury Stock | C67: 0 | D67: -3089 | E67: 0 | F67: 0 | G67: 0 | H67: 0 | I67: 0 | J67: 0 | K67: 0
B68: others | C68: 5721 | D68: -710 | E68: 299 | F68: 3879 | G68: 696 | H68: 809 | I68: -9 | J68: 3194 | K68: -1348
B69: Net Cash from Financing Activities | C69: -71685 | D69: -90245 | E69: -83639 | F69: -100732 | G69: -84666 | H69: -119700 | I69: -128294 | J69: -107685 | K69: -119910
B71: Effect of Exchange Rate Changes | C71: 27949 | D71: 11116 | E71: -25191 | F71: 33292 | G71: 16461 | H71: -179155 | I71: 67452 | J71: 45234 | K71: 45569
B73: net Increase in Cash and Cash Equivalents | C73: 232768 | D73: 100931 | E73: 87654 | F73: 240846 | G73: 267177 | H73: -30280 | I73: 106235 | J73: 297097 | K73: 267781
... B76: Cash and Cash Equivalents at End od Period | C76: 1698196 | D76: 1799127 | E76: 1886781 | F76: 2127627 | G76: 2394804 | H76: 2364524 | I76: 2470759 | J76: 2767856 | K76: 3035637
B79: Balance Sheet
B80: all figures in millions of New Taiwan Dollors NTD | C80: =C2 -> 45352 | D80: =D2 -> 45473 | E80: =E2 -> 45565 | F80: =F2 -> 45657 | G80: =G2 -> 45747 | H80: =H2 -> 45838 | I80: =I2 -> 45930 | J80: =J2 -> 46022 | K80: =K2 -> 46112
B82: Current Assets
B83: Cash and Cash equivalents | C83: 1698196 | D83: 1799127 | E83: 1886781 | F83: 2127627 | G83: 2394804 | H83: 2364524 | I83: 2470759 | J83: 2767856 | K83: 3035637
B84: Investment in Marketable Financial instruments | C84: 224460 | D84: 249508 | E84: 280819 | F84: 294392 | G84: 308281 | H84: 269905 | I84: 280297 | J84: 300738 | K84: 347964
B85: Accounts Receivables | C85: 201980 | D85: 210210 | E85: 249974 | F85: 272088 | G85: 243949 | H85: 235685 | I85: 307814 | J85: 281791 | K85: 363005
B86: Inventories | C86: 267123 | D86: 272491 | E86: 292884 | F86: 287869 | G86: 293388 | H86: 304194 | I86: 288689 | J86: 288110 | K86: 311454
B87: Other Current Assets | C87: 61008 | D87: 60332 | E87: 63456 | F87: 106376 | G87: 105242 | H87: 90610 | I87: 88456 | J87: 178636 | K87: 207452
B88: Total Current Assets | C88: 2452767 | D88: 2591658 | E88: 2773914 | F88: 3088352 | G88: 3345664 | H88: 3264918 | I88: 3436015 | J88: 3817131 | K88: 4265512
B90: Non Current Assets
B91: Long term investments | C91: 138469 | D91: 140220 | E91: 127332 | F91: 149040 | G91: 160793 | H91: 137427 | I91: 148978 | J91: 172370 | K91: 166567
B92: PPE | C92: 3051848 | D92: 3105860 | E92: 3071599 | F92: 3234980 | G92: 3400806 | H92: 3386206 | I92: 3499341 | J92: 3691841 | K92: 3954679
B93: ROU, Intangible and Other Non Current Assets | C93: 144807 | D93: 144626 | E93: 192813 | F93: 219566 | G93: 226024 | H93: 217799 | I93: 269773 | J93: 251682 | K93: 274192
B94: Total Non Current Assets | C94: 3335124 | D94: 3390706 | E94: 3391744 | F94: 3603586 | G94: 3787623 | H94: 3741432 | I94: 3918092 | J94: 4115893 | K94: 4395438
B96: Total Assets | C96: 5787891 | D96: 5982364 | E96: 6165658 | F96: 6691938 | G96: 7133287 | H96: 7006350 | I96: 7354107 | J96: 7933024 | K96: 8660950
B99: Current liabilities
B100: Account Payable | C100: 57610 | D100: 63947 | E100: 70820 | F100: 74227 | G100: 76854 | H100: 84772 | I100: 86386 | J100: 84330 | K100: 99856
B101: paybles to Contractors and Equipment Suppliers | C101: 127179 | D101: 136744 | E101: 125132 | F101: 192635 | G101: 199087 | H101: 161416 | I101: 175430 | J101: 177730 | K101: 243927
B102: Cash Dividends Payable | C102: 181525 | D102: 194600 | E102: 207456 | F102: 220419 | G102: 233394 | H102: 246672 | I102: 259326 | J102: 285258 | K102: 311190
B103: Accrued Expenses and Other Current Liabilities | C103: 647366 | D103: 630549 | E103: 618186 | F103: 717386 | G103: 828696 | H103: 790240 | I103: 678538 | J103: 773775 | K103: 903039
B104: Current Portion of Bonds Payable and Bank loans | C104: 12500 | D104: 23076 | E104: 58805 | F104: 59858 | G104: 61772 | H104: 94214 | I104: 76226 | J104: 136926 | K104: 156242
B105: Total Current Liabilities | C105: 1026180 | D105: 1048916 | E105: 1080399 | F105: 1264525 | G105: 1399803 | H105: 1377314 | I105: 1275906 | J105: 1458019 | K105: 1714254
B107: Non Current Liabilities
B108: Bonds Payable | C108: 955540 | D108: 965314 | E108: 909704 | F108: 926604 | G108: 948257 | H108: 848535 | I108: 880433 | J108: 856228 | K108: 860026
B109: Other Non Current Liabilities | C109: 140455 | D109: 147986 | E109: 153633 | F109: 177233 | G109: 183603 | H109: 163869 | I109: 162190 | J109: 157982 | K109: 154281
B110: Total Non Current Liabilities | C110: 1095995 | D110: 1113300 | E110: 1063337 | F110: 1103837 | G110: 1131860 | H110: 1012404 | I110: 1042623 | J110: 1014210 | K110: 1014307
B112: Total Liabilities | C112: 2122175 | D112: 2162216 | E112: 2143736 | F112: 2368362 | G112: 2531663 | H112: 2389718 | I112: 2318529 | J112: 2472229 | K112: 2728561
B114: Equity Attributable to the Shareholders of Parent
B115: Capital Stock at Par | C115: 259336 | D115: 259336 | E115: 259327 | F115: 259327 | G115: 259326 | H115: 259326 | I115: 259325 | J115: 259325 | K115: 259324
B116: Capital Surplus | C116: 70941 | D116: 70941 | E116: 72390 | F116: 73261 | G116: 73307 | H116: 73326 | I116: 73361 | J116: 73446 | K116: 73666
B117: Legal Capital Reserve | C117: 311147 | D117: 311147 | E117: 311147 | F117: 311147 | G117: 311147 | H117: 311147 | I117: 311147 | J117: 311147 | K117: 311147
B118: Special Capital Reserve | C118: 28021 | D118: 0 | E118: 0 | F118: 0 | G118: 0 | H118: 0 | I118: 181555 | J118: 87284 | K118: 16199
...
